Workbook

Sheet Marcas
A1: Marca | B1: País | C1: Cidade | D1: Principal Característica | E1: Faixa de preço | F1: Preço médio | G1: Site | H1: Instagram | I1: História | J1: Principais relógios | K1: Logo | L1: Site bloqueado | M1: Observações
A2: 1776 Atelier | B2: USA | D2: manufatura independente com foco em relojoaria artesanal moderna | E2: 4 | G2: 1776atelier.com | H2: @1776atelier | I2: A 1776 Atelier foi fundada nos EUA com o propósito de redefinir a alta relojoaria norte-americana — misturando o artesanato tradicional com toques contemporâneos. Cada movimento é desenvolvido com acabamento manual apurado, concebido para ser sinuoso e atemporal. Entre seus modelos icônicos, o Monticello é um destaque notável, exibindo uma sofisticada arquitetura de mostrador esqueleto com numerais romanos e marcadores de horas em forma de estrela, tudo apoiado por um dial texturizado e de impressionante profundidade visual. | J2: Mount Vernon Mount Vernon Aventurine The Monticello
A3: 2CAN | B3: Alemanha | C3: - | D3: modelos de quartz por volta de £30–£35 | E3: 1 | G3: - | H3: - | I3: A 2CAN Professional Timepieces é uma marca alemã que apostou em relógios acessíveis, robustos e de visual esportivo. Com linhas como o Vortex Chronograph (SL1598C CH), a marca entrega design moderno em aço inoxidável escovado e polido, mostradores texturizados sun-guilloché e funcionalidades completas de cronógrafo — minutos, segundos e décimos — além de calendário e bisel ajustável. Os modelos são resistentes à água (5 ATM), utilizam vidro mineral e apresentam caixas de 42 mm com pulseiras de couro de estilo carbono. Há também versões automáticas, encontradas em leilões e coleções, que reforçam a proposta de unir estilo a um preço justo. A filosofia da 2CAN sempre foi oferecer um relógio honesto, funcional e marcante, sem abrir mão da acessibilidade. É a escolha ideal para quem deseja o visual de um cronógrafo profissional, mas dentro de uma faixa de preço democrática. | J3: Vortex Chronograph SL1598C CH SM1597D CH Modelos automáticos raros (vintage)
A4: 2LMX WATCHES | B4: Suíça | C4: Genebra | D4: Manufatura independente de alta relojoaria, conhecida pelos tambores rotativos que substituem mostradores tradicionais | E4: 10 | G4: - | H4: - | I4: A 2LMX Watches nasceu em Genebra pelas mãos de Arnaud Tellier, ex-curador do Museu Patek Philippe, que decidiu transformar sua visão vanguardista em realidade. Criada em 2011, a marca rompeu com a tradição suíça ao apresentar um relógio que aboliu os mostradores convencionais: no lugar deles, tambores rotativos exibem as horas, minutos, segundos e a reserva de marcha, num espetáculo mecânico aberto à contemplação. Produzida em tiragens extremamente limitadas, a 2LMX se consolidou no nicho da haute horlogerie independente, voltada a colecionadores que buscam exclusividade absoluta e design futurista. Cada peça é ao mesmo tempo um instrumento de precisão e uma obra de arte, reafirmando que o tempo pode ser tanto medido quanto admirado. | J4: 2LMX Mechanical Timepiece (edições limitadas com variações de materiais e acabamentos)
A5: 3H Italia | B5: Itália | C5: - | D5: Relógios italianos ultraleves, de design ousado e colorido, com caixas grandes (46–52 mm), equipados com movimentos suíços de quartzo e tratamento luminescente de trítio nos índices e ponteiros. | E5: 2 | G5: marca encontra-se atualmente extinta, sem site funcional | H5: @3hitaliaukwatches | I5: A 3H Italia surgiu com rapidez no cenário europeu, conquistando espaço pela combinação de criatividade, ecletismo, ousadia e tecnologia. Diferente das linhas minimalistas suíças, a marca italiana aposta em cores vibrantes, mostradores marcantes e caixas de grandes dimensões, variando entre 46 mm e 52 mm. O nome “3H” remete ao trítio (³H), material luminescente usado em índices e ponteiros, simbolizando o conceito de leveza e luminosidade. O público-alvo da 3H Italia é formado por pessoas otimistas e cheias de energia, ligadas ao mundo da moda, esportes e vida noturna. Não à toa, celebridades como Shaggy, o cantor Renato Zero e jogadores da seleção italiana, incluindo Leonardo Bonucci, já usaram e declararam seu apreço pela marca. A coleção Ocean Diver reflete bem o DNA da marca, trazendo design moderno, cores chamativas e resistência à água, sempre movida por calibres suíços de quartzo confiáveis.
A6: 47 Zero | B6: França | C6: Chavanod | D6: Microbrand artesanal com mostradores exclusivos, acabamento manual que garante que nenhum relógio seja igual ao outro | E6: 3 | G6: 47zero.com | H6: @the47zero | I6: A 47Zero nasceu nas encostas dos Alpes Franceses, em Chavanod, fundada em 2023 por Cormac Hanley, um irlandês que descobriu a relojoaria durante sua recuperação de um AVC aos 47 anos, o nome “Zero” simboliza um novo começo. Cada relógio 47ZERO é uma obra de arte única: os mostradores são finalizados manualmente, usando técnicas como gravação CNC, laser e polimento artesanal, garantindo que nenhuma peça se repita. O modelo Odd-Hours exemplifica esse espírito, com design assimétrico que desafia convenções e revela detalhes sutis, como parafusos polidos à mão que unem esfera e base do mostrador. Equipados com movimento automático suíço (STP1-11), resistentes até 100 m de profundidade, e disponíveis em 36 mm ou 39 mm, esses relógios entregam uma experiência profundamente pessoal, são menos objetos de status e mais “amuleto líquido de significado”, como descrevem admiradores e colecionadores. | J6: Odd-Hours
A7: 4N Watches | B7: França | C7: Paris | D7: Alta relojoaria contemporânea independente com exibição digital mecânica inovadora por discos giratórios com “jumping hours & minutes” e tiragem extremamente limitada | E7: 10 | G7: 4nparis.com | H7: @4nwatches | I7: A 4N foi fundada em 2009 pelo relojoeiro e designer François Quentin, com o propósito de repensar o modo de exibir o tempo. Movido pela ideia de uma leitura digital totalmente mecânica, inspirada nos mesmos conceitos digitais dos anos 70, Quentin criou o sistema de discos giratórios que mostram as horas e minutos de modo “saltante” (“jumping hours & minutes”). O nome “4N” faz referência aos quatro dígitos utilizados na leitura (tens de horas, horas, dezenas de minutos e minutos). O coração do modelo principal, o 4N-MVT01/D01, é um calibre manual com reserva de marcha de até 10 dias, feito em parceria com a manufatura Renaud & Papi (APRP). A construção é complexa: cerca de 514 componentes, avanço constante de força, acabamento totalmente à mão e ouros compostos e exclusivos, como ouro branco, titânio ou platina, em edições limitadas a 16 unidades. O design é tão técnico quanto estético: caixas robustas e arquitetônicas, mostradores transparentes que revelam o mecanismo, acabamento refinado com alternância entre superfícies polidas e escovadas, e, em alguns casos especiais como o Sapphire Planet, até caixa em safira que revela o movimento em todos os ângulos. | J7: 4N-MVT01/D01 — display digital mecânico por discos, reserva de marcha de 10 dias, edição limitada (16 peças), preços em torno de €150.000
A8: 666 Barcelona | B8: Espanha | C8: Barcelona | D8: Fashion watches com estilo urbano inspirado em Barcelona; design acessível e estético, com display analógico/quartz prático para o dia a dia | E8: 1 | G8: - | H8: - | I8: A 666 Barcelona é uma coleção de relógios com alma urbana, surgida a partir da vibrante atmosfera das Ramblas de Barcelona. Com um visual fashion e urbano, suas peças unem estilo contemporâneo e funcionalidade simples. Disponíveis por preços acessíveis (entre €19 e €29), são ideais para quem busca um acessório com personalidade sem estourar o orçamento. Comercializados principalmente em plataformas online e outlets de moda, esses relógios refletem a estética espanhola moderna — robustos, visualmente charmosos e perfeitos para expressar um estilo cotidiano com atitude. | J8: 666-212, 666-290
A9: 6B Watches | B9: Reino Unido | C9: - | D9: Microbrand artesanal inspirada em relógios militares RAF, com produção limitada, estética funcional e embalagens personalizadas exclusivas | E9: 4 | G9: https://www.gasgasbones.com/ | H9: - | I9: 6B Watches nasceu da paixão de Carl Evans, veterano da Real Força Aérea Britânica (RAF), fundador da marca GasGasBones. Em 2013, após anos lidando com equipamentos militares voltados para funcionalidade no lugar de estética, Carl decidiu materializar sua visão criando o MK1 (uma homenagem aos pilot watches do RAF) em tiragem extremamente limitada com caixa alemã e movimento ETA 7750. O sucesso do MK1 impulsionou a série MK2, com 50 unidades entregues em embalagem elaborada e case de madeira produzido na sede da GasGasBones. Depois, veio o MK3 “Scramble”, de 38 mm, com mostrador militar e embalagem que lembrava um cockpit de Spitfire, incluindo uma caixa "ammo" personalizada com tema operacional. O MKIII Scramble Chronograph, por exemplo, é equipado com movimento Valjoux 7750, vidro de safira antirreflexo, resistência à água de 50 m, acabamento robusto e design pensado para facilitar leitura rápida em ação. A marca é um projeto artesanal e íntimo, Carl desenvolve tudo com honestidade, sem marketing exagerado, com produção pequena e personalização máxima, mantendo sua autenticidade e espírito independente. | J9: MK1 – primeiro modelo, movimento ETA 7750, tiragem de 20 unidades GasGasBones.com MK2 – segunda edição (50 unidades), com embalagens customizadas, straps GasGasBones Hodinkee MK3 “Scramble” – cronógrafo Valjoux 7750, 38 mm, série limitada, embalagens inspiradas em aviões Spitfire
A10: 88 Rue Du Rhone | B10: Suíça | C10: Genebra | D10: Relógios suíços contemporâneos com estética de luxo acessível, design elegante (como mostradores com o “Double 8”), opções em quartzo e automáticos, voltados para um público jovem que busca estilo sem abrir mão da qualidade | E10: 2 | G10: marca encontra-se atualmente extinta, sem site funcional | H10: @88rdr | I10: Criada em 2012 pelos irmãos Pierre e Elie Bernheim — netos do renomado relojoeiro Raymond Weil — a 88 Rue Du Rhone nasceu em Genebra com a ambição de democratizar a relojoaria suíça. O nome evoca a famosa Rua do Ródano, símbolo de elegância no centro da cidade, e o "Double 8" usado no logo traz consigo simbologias de sorte e infinito, reforçando a identidade da marca Wikipedia jurawatches.co.uk . A missão era clara: oferecer relógios de qualidade suíça, com visual sofisticado e preços acessíveis a um público mais jovem, entre os US$ 395 e US$ 995 — muito abaixo do padrão tradicional da alta relojoaria Worn & Wound . Modelos como os da linha Double 8 Origin combinaram mostradores texturizados, cristais brilhantes e detalhes refinados, mantendo a excelência dos mecanismos, em versões quartzo e automáticas. Apesar de todo o sucesso inicial, a marca acabou encerrando suas operações em 2020 após dificuldades financeiras. Ainda assim, permaneceu como um marco significativo na história recente da relojoaria suíça acessível, deixando na memória peças com identidade e charme atemporal | J10: Double 8 Origin
A11: A. Lange & Söhne | B11: Alemanha | C11: Glashütte | D11: Alta relojoaria alemã de manufatura, com movimentos próprios de precisão excepcional, acabamento artesanal refinado e design austero (estilo “teutônico”) | E11: {=INDEX('Tabela de faixa de preços'!$A$1:$A$10,MATCH(1,('Tabela de faixa de preços'!$B$1:$B$10<=F11)*('Tabela de faixa de preços'!$C$1:$C$10>=F11),0))} | F11: 355000 | G11: alange-soehne.com | H11: @alangesoehne | I11: Fundada em 1845 por Ferdinand Adolph Lange em Glashütte, na Saxônia, com a missão de transformar uma região empobrecida num polo de alta relojoaria alemã. A dinastia prosperou por gerações até ser silenciada pela Segunda Guerra e pela posterior estatização na Alemanha Oriental. A marca renasceu em 1990 pelas mãos de Walter Lange, bisneto do fundador, dias após a queda do Muro de Berlim. Coleções como a Lange 1 — com seu icônico calendário grande e o mostrador assimétrico segundo a proporção áurea —, além de Datograph, Zeitwerk, Saxonia e Odysseus, definiram a nova era. É referência absoluta em acabamento: pontes em prata alemã (Neusilber), balanço com parafusos de ouro e o galo do balanço gravado à mão, peça a peça. Cada movimento é montado, ajustado, desmontado e remontado antes da entrega. Virou símbolo do orgulho relojoeiro alemão. [⚠️ verificar dados atuais] | J11: Lange 1, Datograph, Zeitwerk, Saxonia, Odysseus
A12: A. Manzoni & Fils | B12: Suíça | C12: Lugano | D12: Manufatura suíça revivida com design contemporâneo e complicações de calendário semanal (week planner) | E12: 7 | I12: Fundada em 1888 em Arogno (Lugano), a A. Manzoni & Fils ganhou nova vida em 2010 quando Oliver Ike (cofundador da Ikepod) reativou a marca com o designer Ilkka Suppanen. O Canopus Weekplanner (2013) virou assinatura: mostra hora, dia, data, semana do ano e fase da lua, usando módulo Dubois-Dépraz sobre calibre Soprod A10. O projeto combinou estética “retro-futurista” (caixa curva, mostrador multicamadas) com produção Swiss Made em séries curtas. | J12: Canopus Weekplanner
A13: AATOS | B13: China | C13: - | D13: Tourbillon mecânico acessível, marketing agressivo pelo menor preço possível, mas com questionamentos sobre autenticidade e qualidade | E13: 2 | G13: - | H13: - | I13: A AATOS é conhecida por seu ousado posicionamento: oferecer um tourbillon mecânico por menos de £400, um valor que surpreende mesmo dentro do nicho de entrada da relojoaria. O modelo mais falado é o Tiago, um relógio de 42 mm com mecanismo aparentando ser um tourbillon real. No entanto, sua procedência é nebulosa — alguns críticos sugerem que seu DNA pode ser chinês, com qualidade e marketing duvidosos. Ainda assim, despertou curiosidade no mundo relojoeiro como uma proposta inacreditavelmente barata por uma complicação tradicionalmente cara. | J13: Tiago (LSB 42 mm)
A14: Abingdon | B14: USA | C14: Las Vegas | D14: Relógios funcionais e estilizados, desenhados por uma piloto para mulheres ativas; incluem funcionalidades como taquímetro, múltiplos fusos, cronógrafo, bússola e calculadora de voo (“E6B”), com design robusto e moderno | E14: 2 | G14: abingdonco.com | H14: @theabingdonco | I14: Abingdon Co. foi fundada em 2007 por Chelsea Abingdon Welch (Mullin), uma piloto que percebeu a ausência de relógios de aviação projetados para mulheres. Com paixão e visão, ela criou modelos como Jackie e Amelia, lançados em 2007, produzidos inicialmente em Hong Kong. Em 2010, a sede foi transferida para Las Vegas, onde a marca continua inovando a cada coleção. Seu catálogo evoluiu para incluir relógios de mergulho, aviação, corrida e uso militar, todos com funcionalidades práticas como régua de cálculo E6B (útil em caso de pane nos instrumentos de voo), bússola, cronógrafos e resistência à água, aliados a um design pensado para uso real. A Abingdon Co. hoje é reconhecida por empoderar mulheres que desafiam estereótipos e exercem profissões ativas — piloto, mergulhadora, engenheira ou exploradora urbana Wikipedia The Abingdon Co. Worn & Wound Girls that Scuba . Em 2025, a marca inaugurou sua flagship store em Las Vegas e continua atuando como timekeeper oficial de eventos como o Air Race Classic — prova de seu reconhecimento no universo feminino e da aviação | J14: Amelia, Jackie, Marina, Jane, Jordan, Katherine, Nadia, Legends
A15: About Vintage | B15: Dinamarca | C15: Copenhague | D15: Microbrand nórdica que combina design vintage escandinavo minimalista com movimentos confiáveis (Seiko/Miyota e suíços), embalagens refinadas com a silhueta de Copenhague gravada na tampa | E15: 2 | G15: aboutvintage.com | H15: - | I15: Fundada por dois amigos dinamarqueses — Thomas Gyvelgaard Andersen e Sebastian Skov Regeser — em 2013, a About Vintage nasceu com a proposta de reinterpretar clássicos da relojoaria com um olhar moderno e minimalista Independent Watch Brand Addict . Cada modelo leva um nome ligado a um momento marcante da história da relojoaria, como “1815”, “1926”, “1956”, acrescentando poesia à sua estética. Os relógios são cuidadosamente embalados em caixas de madeira com fechamento magnético e a silhueta de Copenhague gravada na parte interna da tampa — cada peça numerada e com assinatura de origem Hype & Style Tick Tock Shop . O design busca equilíbrio entre simplicidade vintage e toques contemporâneos, enquanto os movimentos — automáticos Seiko ou com calibres suíços — garantem confiabilidade e acessibilidade Hype & Style WatchReport.com +1 . A combinação de refinamento estético, cuidado artesanal visual e preço equilibrado transformou a marca numa referência entre os dress watches inspirados no estilo vintage, ideais para quem quer elegância acessível sem abrir mão de personalidade. | J15: 1815 Chronograph — cronógrafo quartz, cerca de €349 (≈ R$ 2.000) AV86 1926 At’ Sea Diver — relógio estilo diver com calibre Seiko VH31, preço por volta de US$ 399 (≈ R$ 2.100) WatchReport.com 1956 Marine — diver vintage com bezel cerâmico e Miyota automático, partindo de US$ 449 (≈ R$ 2.350)
A16: Accutron | B16: USA | C16: Nova York | D16: Marca pioneira da relojoaria eletrônica com tecnologia de diapasão e, hoje, movimentos eletrostáticos modernos que unem inovação tecnológica e legado histórico | E16: {=INDEX('Tabela de faixa de preços'!$A$1:$A$10,MATCH(1,('Tabela de faixa de preços'!$B$1:$B$10<=F16)*('Tabela de faixa de preços'!$C$1:$C$10>=F16),0))} | F16: 16000 | G16: accutronwatch.com | H16: - | I16: A Accutron surgiu em 1960 como uma revolução: o primeiro relógio de pulso totalmente eletrônico — utilizando um diapasão de 360 Hz em vez do tradicional balanço — desenvolvido por Max Hetzel e produzido pela Bulova em Nova York Bulova Australia Wikipedia +1 accutronwatchpage.com . A precisão era impressionante: ±2 segundos por dia, superior à dos mecânicos da época. Esse diferencial fez da Accutron a escolha da NASA, com componentes utilizados em missões espaciais como o Apollo e o Mercury, assim como na superfície lunar durante a Apollo 11 e até relógios de bordo windupwatchshop.com . Após a descontinuação da vibração por diapasão, a marca foi reativada em 2020 como uma entidade independente pelo grupo Citizen. As novas linhas incluem o Spaceview 2020 e o Accutron DNA, movidos por tecnologia inovadora de indução eletrostática, trazendo o DNA futurista da marca à era moderna | J16: Vintage Accutron Spaceview (1960s) — pioneiro do diapasão, visual icônico de mostradores abertos Accutron Spaceview 2020 — reeditação moderna com mecanismo eletrostático Accutron DNA / Evolution — tecnologia futurista, visual contemporâneo
A17: Acto | B17: Brasil | C17: Porto Alegre | D17: Marca independente brasileira de design autoral, com colaborações criativas e especificações de produto bem equipadas (safira, 10 ATM, Super-Luminova, Miyota) em séries curtas | E17: 3 | F17: 3500 | G17: actowatches.com | H17: @acto | I17: Fundada em 2020, a Acto surgiu em Porto Alegre com a proposta de criar relógios de identidade própria — menos “white-label”, mais estética brasileira contemporânea. Ao lado de artistas e designers convidados, a marca foi ganhando tração no mercado local, mantendo comunicação direta e produção em séries limitadas | J17: AC01 (Bourbon, Urban, Outlander, Navigator, Phantom) — R$ 5.970. ACTO AD01 (diversas cores) — R$ 6.730 (algumas edições especiais até R$ 8.790). ACTO +1 PB012 (by Patrícia Bonaldi) — R$ 9.700. ACTO A003 Carbon (by Erich Shibata) — R$ 11.970 (topo pontual). ACTO AS01 Angra (edição limitada) — R$ 4.850 (abaixo da média da marca). ACTO +1 A001 — R$ 3.500
A18: ADPT | B18: USA | C18: - | D18: Marca de lifestyle outdoor que evoluiu de acessórios (pulseiras têxteis) e lançou um relógio multipropósito leve e colorido com caixa de titânio, movimento automático Seiko NH34 e visual exclusivo | E18: 2 | G18: ADPTGoods.com | H18: @adptgoods | I18: ADPT (pronunciado “adapt”) foi fundada em 2017 pelos criadores do Worn & Wound, como uma marca dedicada inicialmente a fabricar pulseiras de nylon mil-spec feitas nos EUA. Com o tempo, se expandiu para oferecer uma linha completa de acessórios e, em 2022, estreou seus primeiros relógios com o Series 1 — esportivo, titaniumado, 200 m de resistência, mostrador texturizado e cores vibrantes, inspirado no outdoor e no universo EDC (Everyday Carry) Island Watch Worn & Wound +1 Fratello Watches . O modelo Series 1 Dual-Time manteve a robustez do original e acrescentou uma complicação GMT (indicador 24 h) movimentada pelo calibre Seiko NH34, mantendo o DNA funcional da marca com forte identidade visual | J18: Series 1 — field watch leve em titânio, 200 m, Seiko NH35, visual colorido Series 1 Dual-Time — funcionalidade GMT com o novo Seiko NH34, mesmas linhas outdoor e modernas Colaborações — edição limitada com VERO (Workhorse Chronograph), consolidando seu status no mundo outdoor e horológico aventureiro | K18: https://windupwatchshop.com/cdn/shop/t/41/assets/adpt-brand-logo.svg?v=137860177147247661051761747591
A19: Adriano Valente | B19: Suíça | C19: Lausanne | D19: Relojoaria de luxo personalizável inspirada nos supercarros italianos, com caixa angular em materiais como Karbonyte, AlTiCar ou magnésio forjado e mostrador que imita um velocímetro | E19: 8 | G19: - (adrianovalente.com, hoje inativo para a marca) | H19: - | I19: A Adriano Valente foi criada por volta de 2010 em Lausanne, na Suíça, por um fundador italiano que não encontrava no mercado o relógio que queria — por isso a personalização virou o centro da proposta. Em 2011 a marca apresentou seu único modelo, o AV-L001, pensado para combinar com uma Lamborghini: caixa angular mais larga que alta, mostrador inspirado no velocímetro, centro que lembra as entradas de ar hexagonais do Murciélago e coroa desenhada como uma roda com freio a disco. Não havia nenhuma parceria oficial com a montadora; a inspiração era apenas estética. O cliente escolhia o material da caixa (Karbonyte, AlTiCar ou magnésio forjado), a cor da caixa — podia ser igual à pintura do próprio carro —, mostrador, pulseira de borracha ou Alcantara, coroa e fundo aberto ou fechado. Pagando à parte, era possível "travar" a combinação para que ninguém mais tivesse um igual. O movimento automático Engine-001A trazia grande data saltante e indicador de reserva de marcha, e o preço partia de 32.500 francos suíços. Depois do lançamento a marca praticamente desapareceu: não há novos modelos nem notícias, e o antigo site hoje pertence a outra pessoa. | J19: AV-L001 — único modelo (2011), movimento Engine-001A com grande data e reserva de marcha, caixa em Karbonyte/AlTiCar/magnésio, 6 cores com nomes no estilo Lamborghini (Nero Tartarus, Giallo Hyperion, Rosso Eos, Grigio Menoetius, Bianco Ophian, Verde Icaria) | K19: https://www.fashionbi.com/rails/active_storage/blobs/redirect/eyJfcmFpbHMiOnsiZGF0YSI6MTg4NCwicHVyIjoiYmxvYl9pZCJ9fQ==--3e6fde9bff4b1ee1abfaa5145820cb739e3a2e61/Adriano%20Valente-logo.jpeg
A20: Aera | B20: Suíça/Reino Unido | C20: Genebra | D20: Microbrand de tool watches contemporâneos com design minimalista e curvas suaves, usando caixa em aço 904L, acabamento suíço e movimentos Sellita | E20: {=INDEX('Tabela de faixa de preços'!$A$1:$A$10,MATCH(1,('Tabela de faixa de preços'!$B$1:$B$10<=F20)*('Tabela de faixa de preços'!$C$1:$C$10>=F20),0))} | F20: 15000 | G20: aera.co | H20: @aerainstruments | I20: A Aera nasceu em 2018, em Genebra, como resultado da parceria entre Jas Minhas e Olof Larsson — veteranos da indústria relojoeira. Movidos por paixão e legado (Minhas com raízes watchmakers e Larsson com histórico de retail), a dupla criou relógios que fossem minimalistas, funcionais e ao mesmo tempo contemporâneos Hodinkee Oracle Time . Com design inspirado nos archetypes dos tool watches — mas reinterpretados com silhuetas suaves, curvas e dials côncavos — Aera lançou modelos como os P-1 Pilot e D-1 Diver, ambos com acabamento em aço 904L, calibres Sellita suíços, e estética limpa e legível Uncrate Hodinkee +1 . A marca se posiciona na interseção entre acessibilidade, design de vanguarda e engenharia tradicional. | J20: P-1 Pilot — tool-watch com movimento Sellita SW200-1, caixa em 904L, mostrador legível, disponível por ~US$ 1.300 (~R$ 6.500) Silodrome D-1 Diver — relógio de mergulho com bezel unidirecional, estilo moderno minimalista Uncrate C-1 Chronograph (Shadow / Cloud) — cronógrafo bicompax com design limpo e movimento Sellita SW51 | K20: https://aera.co/cdn/shop/files/Aera_Logo.png?v=1614349956 | XFD20: ;
A21: Aeromat | B21: Suíça | C21: - | D21: Relógios de aviação contemporâneos (tool watches) com alta legibilidade, uso de materiais técnicos (para-carbono, aço 904L), movimentos suíços/quartz modernos e design inspirado em instrumentos de voo | E21: 2 | G21: aeromatwatches.com | H21: @aeromat_official | I21: Aeromat nasceu da paixão de um grupo de entusiastas por relógios de piloto, com o objetivo de trazer inovação ao gênero. Com coleções como a AEM 450 (inspirada em exigências de pilotos modernos), Airspeed (ensaio estético nas linhas clássicas da Havilland) e o PNY (cronógrafo retrô dos anos 50), a marca se consolidou como referência entre os apaixonados por relógios de aviação acessíveis. A linha VDN homenageia pilotos noturnos e eleva o conceito de tool watch com funcionalidade real para voos | J21: VDN (Vol de Nuit): cronógrafo para voos noturnos, preço ~US$ 490–520 (~R$ 2.600–2.800) AEM 450 / AEM Pilot Edition: relógico leve com case de carbono, ~US$ 490 (~R$ 2.600) PNY: cronógrafo retrô, preço similar (~US$ 480 → R$ 2.600) Airspeed: automático estiloso, preço ~US$ 790 (~R$ 4.300) Beluga: automático robusto, ~US$ 990 (~R$ 5.400) IFR: tool quartz com calculadora de voo, | K21: https://www.aeromatwatches.com/web/image/website/6/logo/Aeromat%20Watches?unique=ee218df
A22: Aeronom | B22: Alemanha | C22: - | D22: Estilo street / urbano robusto com inspirações heavy (cases grandes, bezel agressivo, linhas que lembram relógios “peso-bruto”), acabamento foco em detalhes como índices luminescentes, coroa rosqueada, vidro de safira, resistência de 100m. Marca independente voltada para estética audaciosa com automáticos acessíveis. | E22: 2 | G22: aeronom-watches.com | H22: @aeronom_watches | I22: A Aeronom se apresenta como uma marca para quem gosta de relógio que “faz presença”. Fundada por entusiastas alemães, sua filosofia é tornar “o relógio dos seus sonhos” realidade — mas não um relógio pequeno ou discreto. O modelo Aero One — a cara da marca — é automático, pesado no visual, ousado no design, com bezel grande, índices e mostradores impactantes, tudo pensado para estilo urbano porte grande. Projetado para resistência mínima de uso diário (100m) e construção em aço (316L) com vidro de safira, o Aero One combina robustez com estilo que chama atenção. | J22: Aero One — referência principal da marca; edições como “Big Panda”, “BLK” entre outras; preço ~ €495 (automático com Miyota 8217) AERONOM® +1 Edições limitadas do Aero One (por exemplo, “BLK”, “Panda” etc.) com detalhes de cores e acabamento diferenciados | K22: https://aeronom-watches.com/assets/img/aeronom_logo_w_t.png
A23: Aerowatch | B23: Suíça | C23: La Chaux-de-Fonds | D23: Marca suíça familiar independente, especializada em relógios clássicos e também em relógios de bolso, com estética elegante e complicações acessíveis | E23: 2 | F23: 8000 | G23: aerowatch.com | H23: @aerowatch | I23: A Aerowatch foi fundada em 1910 em La Chaux-de-Fonds, coração da relojoaria suíça, inicialmente focada em relógios de bolso e de pendente. A empresa permaneceu independente ao longo das décadas, passando por gerações da família Crevoisier até chegar à gestão da família Bolzli. Hoje está sediada em Saignelégier, mantendo produção de relógios elegantes com design clássico e mecânica confiável. O catálogo inclui tanto modelos contemporâneos quanto homenagens vintage, mas sempre com a herança da tradição suíça presente. A Aerowatch é especialmente lembrada por seu equilíbrio entre qualidade, design refinado e preço acessível, sendo uma escolha para quem busca sofisticação sem entrar nas cifras mais altas da alta relojoaria. | J23: Les Grandes Classiques — coleção tradicional com design elegante Streamline — linhas modernas com identidade própria 1942 Collection — estética vintage inspirada na década de 40 Pocket Watches / Lepines — continuidade do legado original em relógios de bolso | K23: https://www.aerowatch.com/pub/static/version1765335430/frontend/Procab/aero/en_US/images/logo.svg
A24: Aesop | B24: China | C24: Guangzhou | D24: Marca chinesa de Guangzhou especializada em tourbillons mecânicos de baixo custo e relógios de moda, muito difundida em marketplaces online | E24: 2 | G24: aesoptourbillon.com | H24: @aesoptourbillonofficialstore | I24: A Aesop tem raízes na indústria relojoeira de Guangzhou, na região próxima a Hong Kong, e se estabeleceu como marca própria no início dos anos 2000. Nasceu para levar a estética do tourbillon — normalmente reservada à alta relojoaria — a um público que jamais poderia pagar por ela. O posicionamento é claro: oferecer relógios mecânicos de aparência luxuosa, com destaque para tourbillons esqueletizados e linhas de quartzo masculinas e femininas, vendidos sobretudo por AliExpress, Amazon e lojas de dropshipping. O apelo é a 'complicação impossível' a preço acessível. Divide opiniões entre entusiastas: para alguns é porta de entrada divertida ao mundo mecânico; para outros, exemplo do tourbillon 'decorativo' chinês. De todo modo, ocupa um nicho real de moda relojoeira de massa. [⚠️ verificar dados atuais: fundação, sede exata e catálogo] | J24: Aesop Tourbillon Skeleton, linhas de quartzo masculino e feminino
A25: Aether | B25: USA | C25: Phoenix | D25: Microrrelojoaria americana de relógios sociais de corda manual, com caixa feita em Pforzheim (Alemanha), movimento Unitas 6498 decorado e pulseiras artesanais da Stone Creek Straps | E25: 3 | G25: aetherwatches.com | H25: @aetherwatches | I25: A Æther Watch Co. foi criada em 2012 em Phoenix, no Arizona, pelos donos da Stone Creek Straps, fábrica americana de pulseiras artesanais de couro. A ideia era levar para o relógio o mesmo cuidado artesanal das pulseiras: desenho em Phoenix, caixa e montagem em Pforzheim, na Alemanha, berço da relojoaria alemã. O primeiro e principal modelo foi o AE01, um relógio social de 42 mm com movimento de corda manual Unitas 6498, acabamento Côtes de Genève e parafusos azulados, oferecido com mostradores preto fosco, antracite escovado, marrom escovado, prateado e carmim, além de versão com caixa em ouro rosé. Custava entre US$ 1.350 e US$ 1.500. Em seguida veio a Æther by Jochen Benzinger, edição especial de apenas 25 peças em que o movimento foi redecorado à mão pelo gravador alemão Jochen Benzinger, com guilhoché cortado à mão e balanço gravado banhado a ouro rosé, por cerca de US$ 3.900. Desde meados da década de 2010 a marca não apresentou novos modelos. Atenção: não confundir com a Aether Apparel, marca de roupas outdoor de Los Angeles que em 2023 lançou o relógio Aether + Bamford GMT — é outra empresa. | J25: AE01 — social de corda manual, 42 mm, Unitas 6498 decorado, mostradores preto, antracite, marrom, prateado e carmim (também em ouro rosé) Æther by Jochen Benzinger — edição especial de 25 peças com movimento decorado à mão
A26: Aethia | B26: USA | C26: San Francisco | D26: Microbrand americana de relógios esportivos leves em titânio, com design disruptivo voltado a atividades outdoor e a um público de adrenalina | E26: 2 | G26: aethiawatch.com | H26: @aethiawatchcompany_usa | I26: A Aethia Watch Company nasceu nos Estados Unidos com a proposta de romper tendências e criar designs disruptivos para entusiastas — dos novatos aos colecionadores experientes. Em 2025 mudou a sede para San Francisco, consolidando sua identidade em torno de performance e esportes. Seu primeiro protótipo foi o Activa, relógio esportivo leve em titânio pensado para atividades ao ar livre. Depois veio o PULSIQ (2025), com diversas variantes e melhorias, movendo a linguagem da marca para uma estética de velocidade e adrenalina, reforçada por embaixadores atletas multiesportivos. Como microbrand jovem, aposta em titânio, leveza e visual arrojado como diferenciais frente às marcas outdoor tradicionais, buscando espaço num segmento dominado por nomes consagrados. [⚠️ verificar dados atuais: ano de fundação e fundador] | J26: Activa, PULSIQ | K26: https://aethiawatch.com/cdn/shop/files/LogoWhite.png?v=1700045446
A27: Airain | B27: França | C27: Besançon | D27: Marca militar francesa histórica (1934), revivida em 2020, fiel ao cronógrafo flyback Type 20 da aviação militar francesa | E27: 4 | G27: airain.com | I27: Fundada em 1934 e ligada à célebre dinastia relojoeira francesa Dodane, a Airain teve papel importante na era de ouro dos cronógrafos de aviação militar da França nos anos 1950 e 1960. Foi uma das fornecedoras selecionadas para o Type 20 da Força Aérea, ao lado de nomes como Breguet, Auricoste e Vixa. O Type 20 seguia a especificação militar dos anos 1950: cronógrafo robusto com função flyback, que permitia ao piloto reiniciar a cronometragem instantaneamente sem parar antes. Em 2020 a marca foi revivida por Tom van Wijlick (também por trás da Lebois & Co.), fiel ao conceito original. A reedição trouxe manufatura suíça, cristal de safira e um flyback de roda de colunas da Manufacture AMT, mantendo as especificações militares. A Airain reconquistou até lugar nos pulsos dos pilotos da ALAT francesa. Hoje a marca pertence à Compagnie des Montres Lebois & Cie (CDMLEC), empresa de Tom van Wijlick sediada em Reuver, na Holanda, e os relógios são produzidos na Suíça. | J27: Type 20, Type 21, Sous-Marine (mergulho, reedição do modelo de 1962), Voyageur GMT (2025) | K27: https://www.airain.com/wp-content/uploads/2022/06/LOGO_AIRAIN_def-500x200-1.png
A28: Aision | B28: Hong Kong | C28: Hong Kong (Tsim Sha Tsui) | D28: Microbrand de design minimalista, focada em estética depurada e nos detalhes mais sutis | E28: 2 | G28: aisiondesign.com | I28: A Aision Design é uma microbrand relojoeira construída sobre uma filosofia de design baseada no essencial. Sua missão declarada é apresentar uma estética única por meio do design e da produção, encontrando beleza nos menores detalhes. O mundo ao redor serve como fonte constante de inspiração para a marca, que traduz esse olhar em peças minimalistas e depuradas. As informações públicas ainda são escassas, o que é típico de microbrands em fase inicial. Como muitas marcas independentes emergentes, aposta na identidade visual limpa e no apelo direto ao consumidor pela internet. A AISION Design é de Hong Kong e tem como designer Lee Cheuk Chung. Estreou em 2018–2019 com o AN-S01, um automático de inspiração espacial lançado no Kickstarter, seguido em 2020 dos AN-S03 (hora em discos) e AN-S04, com caixa de 45 mm e visual de "OVNI". Hoje o catálogo gira em torno da série HANG (incluindo o mergulhador HANG Abyssus, o HANG GMT e a linha artesanal HANG Crafts com folha de ouro e prata), do KONG, do NGIZED Layer-0 de mostrador "suspenso", do CMYK e de três famílias de tourbillon (AN-T01, AN-T02 e AN-T03), muitas com mostradores de pedras como meteorito, charoíte e pietersita. | J28: HANG / HANG Abyssus (mergulho) / HANG GMT / HANG Crafts — automáticos com mostradores de pedra, esmalte e madrepérola Tourbillon AN-T01, AN-T02 e AN-T03 NGIZED Layer-0, KONG, CMYK AN-S01, AN-S03 e AN-S04 — primeiros modelos de inspiração espacial (2019–2020)
A29: Aittokoski Timecrafts Fractalis | B29: Finlandia | C29: Jyväskylä | D29: Relojoaria independente finlandesa de Timo Aittokoski, engenheiro que aplica soluções construtivas não convencionais às caixas e mostradores | E29: {=INDEX('Tabela de faixa de preços'!$A$1:$A$10,MATCH(1,('Tabela de faixa de preços'!$B$1:$B$10<=F29)*('Tabela de faixa de preços'!$C$1:$C$10>=F29),0))} | G29: aittokoski.watch | I29: A Aittokoski Timecrafts é uma marca independente de Jyväskylä, na Finlândia central, fundada por Timo Aittokoski — doutor em ciência da computação e mestre em ciência do esporte, com raízes fincadas no interior finlandês. Antes dos relógios, ele já projetava motos turbinadas, motores dois-tempos de competição, dinamômetros e eletrônica de controle. Depois de uma busca frustrada pelo 'relógio dos sonhos', Aittokoski passou três anos desenvolvendo sua estreia, o Fractalis, lançado em 2019. A peça mistura tradição e futurismo: cristal protegido por bezel, fundo que não rotaciona, lugs-compressores intercambiáveis que unem bezel, caixa e fundo, e um mostrador maciço em aço. O portfólio evoluiu para os modelos Fractalis, R-27 e Quantalor, todos marcados pela mentalidade de engenheiro e por soluções mecânicas fora do convencional. O Fractalis tem caixa de 42 mm × 10 mm com movimento ETA 2892-A2 e é oferecido em aço 316L, "super aço" 2205 ou titânio, inclusive na versão Carbon Black com mostrador de cobre maciço. O R-27 traz caixa hexagonal inspirada em favos de mel, com mostradores Deepest Black ou Arctic Steel e opção de PVD preto. O Quantalor, à venda desde setembro de 2023, tem as versões Glacial Steel e Black Moon. Todos podem ser personalizados com gravações. | J29: Fractalis, R-27, Quantalor | K29: https://static.wixstatic.com/media/a512cf_34a398ba1fbb459299bbfccec73f188f~mv2.png
A30: Akerfalk | B30: Suécia | C30: Karlstad | D30: Microbrand sueca de relógios de 24 horas, com minimalismo escandinavo e pulseiras em couro Horween | E30: 2 | G30: akerfalk.se | I30: A Akerfalk é uma microbrand sueca que fez do relógio de 24 horas sua marca registrada, traduzindo o minimalismo escandinavo em peças de design limpo, equilibrado e atemporal. A proposta une simplicidade nórdica a preços acessíveis, com venda direta ao consumidor. Estreou com o modelo First Season, sua leitura contemporânea do minimalismo, e depois expandiu a linha: o Second Season reduziu a caixa de 40 mm para 36 mm, tornando-o unissex; o Chronograph adotou movimento meca-quartz Seiko VK-64 com subdial de 24 horas; e o Äventyr trouxe novos acabamentos. As pulseiras são feitas em couro Horween 100%, que ganha caráter com o tempo. Com alguns anos de estrada, frete global grátis e dois anos de garantia, a marca firmou seu nicho de design escandinavo acessível. A marca foi fundada em 2016 em Karlstad, na Suécia, por três amigos vindos da moda — Mikael Söderberg, Joakim Lidbäck e Anders Lipkin — e lançou seu primeiro relógio por financiamento coletivo no Indiegogo em 2017. Os relógios usam movimentos suíços Ronda e couro americano Horween, com caixas prata, dourada ou preta fosca. A novidade mais recente é o Mecha Quartz. | J30: First Season — 24 horas, 40 mm, caixa prata, dourada ou preta Second Season — 24 horas, 36 mm, unissex Chronograph 12h/24h — meca-quartz Seiko VK-64 (Panda, Lake, Forrest) Äventyr 24-Hour (Vanta Black, Dull Steel) Mecha Quartz (lançamento mais recente)
A31: Akhor | B31: Suíça | C31: Meyrin | D31: Alta relojoaria independente de Genebra (2025), com mostrador de discos sobrepostos patenteado e certificação Poinçon de Genève | E31: 8 | G31: akhor.ch | I31: A Akhor é uma das mais jovens manufaturas a entrar no círculo da alta relojoaria independente: estreou no Geneva Watch Days de 2025, fundada naquele ano em Genebra (Meyrin) por Anissa Bader, cofundadora e CEO, também presidente da Clamax — fornecedora de componentes de movimento da região de Genebra que é a parceira de produção da marca e detém a patente do mostrador de dois níveis. Nasceu ao redor de uma ideia poética — o 'tempo em equilíbrio' — e de uma visão bastante original do próprio tempo. Sua coleção de estreia, a Le Temps en Équilibre, traz a assinatura da marca: uma arquitetura de mostrador de discos duplos patenteada, em que os ponteiros de horas e minutos giram sob a placa superior e se revelam apenas parcialmente, como suspensos em movimento. A caixa cushion de 39 mm vem em ouro ou aço, e a Nour la Lumière acrescenta um terceiro disco com indicação dia/noite. No coração bate o calibre AK10, de corda manual, 4 Hz e 60 horas de reserva, desenvolvido com apoio do consultor Daniel Martinez. Toda a coleção carrega o Poinçon de Genève — a mais alta distinção suíça — além de certificação COSC. Os preços partem de CHF 28 mil. O catálogo já soma mais de 20 versões do AK-10: em aço (CHF 28.800), aço com 120 diamantes na luneta (a partir de CHF 38.800), ouro 4N/5N (CHF 57.800) e ouro com diamantes, com mostradores raiados ("sunburst") ou em favo de mel ("honeycomb") e, desde 2026, discos em pedras como maw sit sit, estromatólito, jaspe e cianita. No topo estão os Nour La Lumière em ouro e platina (CHF 198 mil e 208 mil), com gravação à mão e pintura em miniatura de um dromedário nas dunas. | J31: Le Temps en Équilibre AK-10 — aço, aço com diamantes (AK-10-D) e ouro (AK-10-AU), mostradores sunburst ou honeycomb AK-10 em pedras ornamentais — Maw Sit Sit, Stromatolite, Deschutes Jasper, Yellow Kyanite, Ruby Heart, Tiger Iron Nour La Lumière (AK-10-AU-JN / AK-10-PT-JN) — dia/noite com terceiro disco, gravação e pintura em miniatura | K31: https://akhor.ch/akhor-logo.svg?v=2
A32: Akrivia | B32: Suíça | C32: Genebra | D32: Alta relojoaria independente de Rexhep Rexhepi, com acabamento artesanal excepcional no estilo da escola genebrina clássica | E32: {=INDEX('Tabela de faixa de preços'!$A$1:$A$10,MATCH(1,('Tabela de faixa de preços'!$B$1:$B$10<=F32)*('Tabela de faixa de preços'!$C$1:$C$10>=F32),0))} | F32: 1000000 | G32: rexheprexhepi.com (antigo akrivia.com) | I32: A Akrivia foi fundada em 2012 em Genebra por Rexhep Rexhepi, relojoeiro de origem kosovar que emigrou criança para a Suíça e se formou nas oficinas de Patek Philippe e BNB Concept antes de abrir a própria manufatura ainda muito jovem. O nome vem do grego para 'precisão' e 'exatidão'. De peças complexas iniciais, Rexhepi migrou para uma linguagem de sobriedade clássica com o Chronomètre Contemporain, celebrado por unir mostrador em esmalte grand feu, acabamento à moda antiga e uma pureza estética que o tornou um dos independentes mais desejados do mundo. O ateliê ocupa a histórica Vieille Ville de Genebra. Cada relógio é montado à mão em séries mínimas, com acabamentos feitos segundo técnicas do século XIX — chanfros polidos à mão, pontes graníteas, cabeças de parafuso polidas em espelho. Virou símbolo do renascimento da alta relojoaria artesanal independente. A primeira fase da marca (Chapter I) foi a dos tourbillons numerados de AK-01 a AK-05, entre 2012 e 2016, seguidos do AK-06 em 2017, primeiro modelo sem tourbillon. Em 2018 nasceu a linha assinada "Rexhep Rexhepi" com o Chronomètre Contemporain (RRCC), seguido em 2022 do RRCC II em ouro rosa e platina (50 peças cada). Vieram ainda o Chronomètre Antimagnétique, peça única para o Only Watch 2023 (cerca de US$ 2,3 milhões), o LVRR-01 Chronographe à Sonnerie com a Louis Vuitton (2023) e, em 2026, o Chronograph Flyback RRCHF (CHF 150 mil). A produção gira em torno de 50 relógios por ano, vendidos por lista de espera, e o site oficial hoje é rexheprexhepi.com. | J32: Chronomètre Contemporain (RRCC) e RRCC II — esmalte grand feu, segundos mortos Chronograph Flyback RRCHF (2026) LVRR-01 Chronographe à Sonnerie (com Louis Vuitton) AK-01 a AK-05 — tourbillons; AK-06 | K32: https://maj.akrivia.com/wp-content/themes/akrivia/assets/images/logo_akrivia_lplv.svg
A33: Akrone | B33: França | C33: Nantes | D33: Manufatura francesa independente que cria relógios automáticos com produção local em Nantes, parceria com elite militar francesa e proposta de "Made in France" | E33: 2 | F33: 2500 | G33: akrone.fr | H33: @akrone_official | I33: Fundada em 2015 em Nantes por Jean-François Kerboul e Erwan Kerneur, a Akrone tornou-se a primeira casa relojoeira francesa a lançar um projeto via Kickstarter (K-01, setembro de 2015), inspirando o renascimento da relojoaria independente francesa. O nome vem do grego "achrone" ("fora do tempo") com o "K" referenciando os fundadores. A marca possui ateliê próprio em Nantes onde controla design, montagem e ajuste, usando movimentos Sellita, ETA, France Ébauches, Citizen e Seiko, e materiais como titânio, aço 316L, cerâmica e carbono. Mais de 100 projetos para o exército francês (ALAT, Legião Estrangeira) e aviação civil (Air France, Transavia) demonstram sua expertise. O modelo K-02 foi certificado "Tête de Vipère" e testado em mergulho recorde a 267m. | J33: C-02 Nérée (mergulho, muitas cores) / C-02 Héritage e Baby Héritage / C-02 Tactik Evo C-03 Horizon, Worldtimer, GMT e Carbon Fury (aviação, titânio e carbono) S-05 (cronógrafo meca-quartz) Históricos: K-01 (2015), K-02, K-03 GMT, K-04, K-05 Chronographe, C-04 | K33: https://akrone.fr/cdn/shop/files/akrone-logo-black.svg?v=1741343267
A34: Akura | B34: Reino Unido | C34: Dundee | D34: Microbrand escocesa com design inspirado nas Highlands; uso raro de bezel interno de bússola controlado por segunda coroa; tool watch acessível | E34: 2 | F34: 2700 | G34: akuratime.com | H34: @akuratime | I34: A Akura nasceu em novembro de 2017 em Dundee, Escócia, fundada pelo designer Philipp Schönfisch. O nome deriva do alemão "akkurat" (preciso), homenageando suas raízes. Após 18 meses de iteração com a comunidade relojoeira, lançou seu primeiro modelo, o Wayfarer, via Kickstarter em 2019 com preço promocional de £399. Inspirado nas Scottish Highlands, o Wayfarer combina caixa de aço 316L de 41mm, cristal de safira, resistência de 100m, movimento Miyota 9015 com rotor customizado e — diferencial raro — uma segunda coroa que controla bezel interno rotativo de bússola. ATENÇÃO: marca aparenta estar inativa após o Kickstarter inicial; verificar status antes de postar. | J34: Wayfarer (único modelo lançado, várias variações de cor)
A35: Alain Silberstein | B35: França | C35: Besançon | D35: Alta relojoaria de design Bauhaus com cores primárias (vermelho, azul, amarelo) e formas geométricas (triângulo, círculo, quadrado); marca encerrada em 2012, hoje vive em colaborações de luxo | E35: 5 | F35: 21000 | G35: marca encerrada em 2012; ver colaborações em louiserard.com, mbandf.com | H35: (sem perfil oficial; ver @louiserardwatches, @mbandf) | I35: Nascido em 1950 em Besançon, Alain Silberstein era arquiteto de interiores treinado em Paris quando, em 1987, apresentou seu primeiro relógio na feira de Basileia ao lado de pioneiros como George Daniels, Svend Andersen e Franck Muller. Em 1990 estabeleceu sua marca homônima, produzindo peças audaciosas com cores primárias e formas geométricas inspiradas em Kandinsky, Picasso e Miró. A marca fechou em 2012, mas seu legado se manteve vivo em colaborações com MB&F (HM2.2 Black Box em 2009, LM1 em 2016), Romain Jerome, Ressence (Carpe Diem) e, desde 2019, Louis Erard — cuja primeira parceria, o Régulateur, esgotou em horas e venceu o Red Dot Award 2021. A trilogia Le Triptyque (limitada a 178 peças cada) consolidou seu retorno como referência viva da relojoaria de design. | J35: Krono Bauhaus | Bolido | Marine GMT | Klok | Louis Erard x AS Régulateur / Le Triptyque | MB&F LM1 Silberstein | K35: https://watch-wiki.org/images/1/1d/Alain_Silberstein_Logo.jpg
A36: Albert Riele | B36: Suíça | C36: La Chaux-de-Fonds | D36: Marca suíça histórica (140+ anos) hoje pertencente ao grupo polonês R2 Trade, com estética clássica, movimentos Ronda/ETA/Sellita e preços acessíveis dentro do segmento Swiss Made | E36: 2 | F36: 3000 | G36: albertriele.ch | H36: @albertriele | I36: Em setembro de 1881, Rodolphe Albert Rielé registrou seu nome de família como marca em La Chaux-de-Fonds — coração da relojoaria suíça. Em 1894, mudanças nas leis de marcas suíças geraram o famoso acrônimo "RAR". Rielé já trabalhava como relojoeiro desde a década de 1860 e conquistou prêmios em exposições de relojoaria, com seus movimentos certificados "Bulletins 1ère Classe" pelos predecessores do COSC. Hoje, a Albert Riele faz parte do grupo polonês R2 Trade, especializado em joias e relógios, que também opera as marcas Bergstern, Aztorin, Elixa e AM:PM. Em 2016, celebrou seu 135º aniversário com a coleção comemorativa Family 1881, incluindo série limitada de 135 relógios de bolso mecânicos. A marca patrocina eventos de vela (World Match Racing Tour) e equestrianismo. | J36: Premiere (cronógrafo flagship) | Concerto | Gala (linha feminina) | Family 1881 | Challenger | K36: https://albertriele.ch/img/albert-riele.png
A37: Albishorn | B37: Suíça | C37: La Chaux-de-Fonds | D37: Manufatura suíça independente do conceito "Imaginary Vintage®" — relógios que parecem de uma era passada mas são novos, com movimentos próprios certificados COSC e produção em séries limitadas | E37: 5 | F37: 22000 | G37: albishorn-watches.ch | H37: @albishorn_watches | I37: A Albishorn foi fundada por Sébastien Chaulmontet e Fabien Collioud em La Chaux-de-Fonds, ambos com forte bagagem na alta relojoaria suíça. Chaulmontet foi Diretor de Inovação da Manufacture La Joux-Perret de 2008 a 2017, liderando a inovação das marcas Arnold & Son e Angelus, e atualmente é Head of Innovation and Marketing na Sellita Watch Co. Também é autor do livro "Chronograph for Collectors". A proposta é criar "Imaginary Vintage®" — relógios que se encaixam perfeitamente na história da relojoaria mas têm caráter próprio, como "elos perdidos" entre eras clássicas. O Type 10 (2024) é apresentado como o ancestral imaginário do Type 20 do exército francês. A marca já lançou colaboração com a Massena LAB (Maxigraph). Os preços (CHF 3.650-3.950) posicionam a marca no segmento independente de luxo, abaixo de competidores diretos. | J37: Type 10 Classic (1948 pilot monopusher) | Thundergraph Himalaya (1952 alpinist) | Marinagraph (1958 dive) | Maxigraph (com Massena LAB) | K37: https://albishorn-watches.ch/svg/logo.svg
A38: Alcadus | B38: Malásia | C38: Kuala Lumpur | D38: Microbrand malaia de design discreto e elegante com acabamento manual, garantia "Worry-Free" de 4 anos cobrindo até substituição de caixa, e revestimento anti-arranhão de 800 HV | E38: 2 | F38: 3500 | G38: alcadus.com | H38: @alcadus | I38: A Alcadus foi fundada em 2018 em Kuala Lumpur, Malásia, pelo entusiasta Yook Hong, que começou sua jornada modificando relógios Seiko antes de criar a marca. O nome combina o latim "altus" (elevado, nobre, profundo) com "cadence" (batida, ritmo do movimento mecânico). A proposta é oferecer relógios premium porém acessíveis com design discreto e elegante. A Quantra — quinta coleção da marca — usa movimento Hangzhou micro-rotor 5015A regulado a +/- 7s/dia, em caixa de 36mm com apenas 10,5mm de espessura, com preço de lançamento de US$ 635. O Voyager Worldtimer GMT vem com Miyota 9075 regulado in-house, caixa de 39mm, vidro de safira em formato "box" com 5 camadas de antirreflexo e resistência de 200m. Diferencial: garantia de 4 anos que cobre até substituição da caixa por danos de uso diário. | J38: Quantra (dress, Type 01/02/03) | Voyager Worldtimer GMT | Opus 39 V2 (dress diver) | Dromo (skin diver vintage) | K38: https://alcadus.com/wp-content/themes/moderno-child/assets/brand/alcadus-lockup-stacked-ink.png
A39: Alchemists | B39: Suíça | C39: Saignelégier | D39: Alta relojoaria com case em liga Cuprum 479 | F39: 1200000 | G39: alchemists.swiss | H39: @alchemists_watches | I39: Alchemists é uma jovem manufatura suíça independente que estreou no Baselworld 2019 com o Cu29 Chapter 1, finalista do GPHG 2019. A marca produz cerca de uma peça por mês, e seu diferencial é o material exclusivo "Cuprum 479" — uma liga patenteada de cobre, ouro e prata. O movimento manual feito in-house tem 51 rubis e reserva de 72 horas, com acabamento aprovado pelo lendário Philippe Dufour. Cada peça custa próximo de CHF 200.000. | J39: Cu29 Chapter 1
A40: Alessandro Baldieri | B40: Itália | C40: Roma | D40: Design italiano com cases robustos | E40: 1 | F40: 1500 | G40: bensontrade.com (revendedor) | H40: @alessandrobaldieri | I40: Alessandro Baldieri é um designer italiano formado em arquitetura e design de interiores em Los Angeles, conhecido por projetar residências de celebridades como Nicolas Cage e Lionel Richie. Em 2006 lançou sua linha de relógios sob o próprio nome, com design italiano contemporâneo, cases robustos (a partir de 44mm) e combinações ousadas de cores. Também é fundador da marca Trifoglio Italia. | J40: Seamonster (SM-46, Panarea), Magnum M-48, Skull Project, Retrospec, End of Time | K40: https://bensontrade.com/dynamic/brand_logos/alessandro-baldieri_1.png
A41: Alessandro Staffetta (AS) | B41: Itália | C41: Bréscia | D41: Microbrand artesanal estilo industrial | E41: {=INDEX('Tabela de faixa de preços'!$A$1:$A$10,MATCH(1,('Tabela de faixa de preços'!$B$1:$B$10<=F41)*('Tabela de faixa de preços'!$C$1:$C$10>=F41),0))} | F41: 4000 | G41: as-watches.com | H41: @as___watches | I41: AS Watches é uma microbrand italiana criada por Alessandro Staffetta, apaixonado por carros, motos e karts desde a infância. Cada peça é construída artesanalmente como única, com cases CNC milled em aço 316L, vidro de safira ou plexiglass tradicional, e movimento ETA 2824. As referências mais conhecidas são o Big One (48mm × 52mm × 18,5mm de espessura) e o Pato (44mm × 52mm), ambos com forte estética industrial. | J41: Big One, B1S, Pato | K41: https://images.squarespace-cdn.com/content/v1/60f5e90f63b0a630fa9ef862/849a4925-bff5-4e24-87df-8a44a48886c0/LOGO_AS.jpg?format=1500w
A42: Alex Benlo | B42: Suíça | C42: Hong Kong | D42: Mostradores em pedras naturais (jade, tigre, malaquita) | E42: {=INDEX('Tabela de faixa de preços'!$A$1:$A$10,MATCH(1,('Tabela de faixa de preços'!$B$1:$B$10<=F42)*('Tabela de faixa de preços'!$C$1:$C$10>=F42),0))} | F42: 6000 | G42: alexbenlo.com (loja: shop.alexbenlo.com) | H42: @alexbenlo | I42: Alex Benlo foi lançada em julho de 2015 em Hong Kong por Eric Loth, executivo veterano da indústria suíça que havia relançado a Graham Watches em 1995. A marca é uma operação familiar que se inspira na conexão entre o homem e a natureza, fabricando timepieces Swiss Made com mostradores feitos de pedras naturais como jade, olho-de-tigre, quartzo e malaquita. Cada mostrador é esculpido à mão, tornando cada relógio único. A campeã de tênis Martina Hingis é embaixadora da marca. | J42: Jade Collection, Tiger Eye, Silver Dragon
A43: Alexander James | B43: USA | C43: Chicago | D43: Microbrand americana com origem em mods Seiko | E43: 2 | F43: 3000 | G43: alexanderjameswatches.com | H43: @alexanderjameswatches | I43: Alexander James Watches é uma microbrand americana sediada em Chicago, fundada em 2014 pelo entusiasta AJ. Tudo começou com mods de Seiko até virar negócio em tempo integral. Cada relógio é montado à mão em Chicago, com atenção meticulosa ao detalhe. O modelo principal é o A3 Omen ($625-$650), com movimento Miyota 9039, sucessor da linha anterior baseada em Seiko NH35. | J43: A3 Omen, A3 Omen II, A3 Meteorite, A5 Legacy X, A5 Reserve, A4 Prelude GMT | K43: https://cdn.watchtraderhub.com/brands/7c1a3af3-e1e6-49be-b6f1-cf87e291df4a/logo-1778436861104-NPDV_oQhtn.webp
A44: Alexander Shorokhoff | B44: Alemanha | C44: Alzenau (Baviera) | D44: Manufatura alemã com filosofia "Art on the Wrist" | E44: {=INDEX('Tabela de faixa de preços'!$A$1:$A$10,MATCH(1,('Tabela de faixa de preços'!$B$1:$B$10<=F44)*('Tabela de faixa de preços'!$C$1:$C$10>=F44),0))} | F44: 18000 | G44: alexander-shorokhoff.com | H44: @alexandershorokhoff_official | I44: Alexander Shorokhoff é uma manufatura alemã fundada em 1992 em Alzenau (Baviera) por Alexander Shorokhov, russo nascido em Moscou em 1960 que veio para a Alemanha em 1991. Após relançar a marca russa Poljot na Europa, criou em 2003 sua própria manufatura. A filosofia "Art on the Wrist" resulta em relógios com mostradores artísticos inspirados em suprematismo russo, art nouveau e figuras como Dostoiévski, Tolstói, Tchaikovski e Pushkin. Movimentos ETA, Sellita e calibres próprios são refinados e gravados à mão na manufatura. | J44: Crazy Balls, Babylonian, Tolstoi, Tomorrow Tourbillon
A45: Alexandre Meerson | B45: Reino Unido | C45: Londres | D45: Casa de design bespoke entre Paris, Suíça e Londres | E45: 5 | F45: 25000 | G45: meerson.com | H45: @meerson_watches | I45: Alexandre Meerson fundou sua casa de design em 2007 e lançou o primeiro relógio em 2014, sendo a terceira geração de relojoeiros e designers da família — seu pai Emerich foi designer celebrado pós-guerra para Tiffany, Mikimoto e H.Stern. Projetada em Paris e fabricada na Suíça, a marca foca em peças bespoke e made-to-order com estética minimalista. Os relógios são destinados a colecionadores que valorizam o processo personalizado de criação. Coleções: Altitude (dress), D15 (sport em titânio/ouro), Mutiny Chronograph e Palatine (feminina). | J45: Altitude, D15, D15 GMT, Mutiny Chronograph, Palatine | K45: https://cdn.watchbase.com/brand/alexandre-meerson-50.png
A46: Alexis Garin | B46: Suíça | C46: Le Locle | D46: Alta relojoaria com esmaltes grand feu e esqueletos | E46: {=INDEX('Tabela de faixa de preços'!$A$1:$A$10,MATCH(1,('Tabela de faixa de preços'!$B$1:$B$10<=F46)*('Tabela de faixa de preços'!$C$1:$C$10>=F46),0))} | F46: 350000 | G46: alexisgarin.ch | H46: @alexisgarin_watches | I46: Alexis Garin (1939-2020) foi um mestre relojoeiro suíço formado pelo Technicum de Le Locle. Após passar por grandes manufaturas e por um período no Piaget, fundou sua marca em 1986 no Val de Travers/Vallée de Joux, dedicando-se à arte do único — peças unitárias, tourbillons, esqueletos hand-made e mostradores em esmalte grand feu. Hoje a marca segue ativa pelas mãos de Fabrice Pancini, mantendo a alma artesanal de Garin, sem produção industrial. Garantia de 10 anos desde 2021. | J46: Tourbillon Squelette, Oxy Lavaux | K46: https://alexisgarin.ch/wp-content/uploads/2026/04/AG_LOGOTYPE.svg
A47: AleXora | B47: Suíça | C47: Zurique | D47: Marca centenária relançada com relógios triangulares | E47: {=INDEX('Tabela de faixa de preços'!$A$1:$A$10,MATCH(1,('Tabela de faixa de preços'!$B$1:$B$10<=F47)*('Tabela de faixa de preços'!$C$1:$C$10>=F47),0))} | F47: 2000 | G47: alexorawatches.com | H47: @alexorawatches | I47: AleXora é uma marca suíça com longa tradição, fundada em 1876 no Vallée de Joux. Esteve no mercado global por 100 anos, fabricando relógios completos incluindo movimentos próprios em La Chaux-de-Fonds — calibres usados também por marcas como "Geneva" e "LeCoultre". A empresa foi premiada por inovação já em 1889. Após décadas de hibernação, foi relançada com sede em Zurique e ficou conhecida pelos relógios triangulares da coleção "Power of Love", inspirados no símbolo da feminilidade. | J47: Power of Love | K47: https://cache.pressmailing.net/thumbnail/small/d706d8d5-b1df-4d2b-8ca2-98b616027ee3/logo
A48: Alfex | B48: Suíça | C48: Manno-Lugano (Ticino) | D48: Design suíço premiado com Red Dot Award | E48: {=INDEX('Tabela de faixa de preços'!$A$1:$A$10,MATCH(1,('Tabela de faixa de preços'!$B$1:$B$10<=F48)*('Tabela de faixa de preços'!$C$1:$C$10>=F48),0))} | F48: 1500 | G48: alfex.com | H48: @alfexwatches | I48: Alfex tem origem em 1948, quando Ferdinand Gindraux fundou a Ferex SA em Lugano. Em 1974, a empresa foi rebatizada Alfex S.A. (fusão de "Alfa" e "Ferex"). É a única marca relojoeira originária do Ticino, região italianófona da Suíça, e mantém-se independente desde então. Em 1981 o CEO Hans Saurer redirecionou a marca ao foco em design, conquistando vários Red Dot Awards. Trabalha com movimentos ETA, Ronda, Valjoux e Unitas, e tem como embaixador o esquiador olímpico Bernhard Russi. | J48: Flat Line, Bernhard Russi Collection, Cervino
A49: Alfred Rochat & Fils | B49: Suíça | C49: Les Bioux (Vallée de Joux) | D49: Manufatura familiar especializada em complicações e esqueletos | E49: {=INDEX('Tabela de faixa de preços'!$A$1:$A$10,MATCH(1,('Tabela de faixa de preços'!$B$1:$B$10<=F49)*('Tabela de faixa de preços'!$C$1:$C$10>=F49),0))} | F49: 45000 | G49: arola-alfred-rochat.ch | H49: @arola_alfredrochat | I49: Alfred Rochat & Fils SA (AROLA) é uma pequena empresa familiar fundada em 1885 no coração da "Watch Valley" suíça, em Les Bioux (Vallée de Joux). Especializa-se em movimentos e complicações: esqueletizações, fases de lua, calendários, GMT, repetições, cronógrafos — frequentemente baseados em ETA Valjoux 7750/23/72/88, Unitas 6497 e ETA 2892-A2. Possui calibres próprios "tonneau" AR 165 e AR 140. A empresa atende várias marcas e também vende relógios próprios sob o nome AROLA. | J49: Lunar, Triple Calendar Moon Chronograph, Squelette | K49: https://arola-alfred-rochat.ch/_media/img/xlarge/logo-3.png
A50: Allemano | B50: Itália | C50: Turim | D50: Misuratori del Tempo inspirados em manômetros vintage | E50: {=INDEX('Tabela de faixa de preços'!$A$1:$A$10,MATCH(1,('Tabela de faixa de preços'!$B$1:$B$10<=F50)*('Tabela de faixa de preços'!$C$1:$C$10>=F50),0))} | F50: 11000 | G50: allemanotime.it | H50: @allemanotime | I50: Allemano é uma empresa italiana de instrumentos de precisão fundada em 1856 por Giuseppe Allemano em Turim, originalmente fabricante de rolos compressores a vapor para construção de estradas. Evoluiu para manômetros, termômetros e instrumentos de medição embarcados em navios, aviões, submarinos e nos primeiros automóveis italianos — o FIAT 501 Torpedo de 1919 trazia um manômetro Allemano. Em 2019 entrou na relojoaria com a coleção "Misuratori del Tempo", inspirada nos próprios manômetros, com cases de 44mm e movimentos suíços Sellita e ETA refinados. | J50: Grande Turino, GMT, Day, MAN, SH 1973 | K50: https://www.allemanotime.it/live//assets/media/site/logo.png
A51: Alludens | B51: Reino Unido | C51: Londres | D51: Sports-luxe inspirado no ciclismo de estrada | E51: 2 | F51: 2000 | G51: alludens.com | H51: @alludens | I51: Alludens (do latim "alludens", esportivo) é uma microbrand de Londres fundada por Freddie Wyatt, dedicada ao conceito sports-luxe. A inspiração vem da estética do ciclismo de estrada vintage e do peloton — o nome Patron é uma referência ao "Patrão do Pelotão". Os relógios combinam design esportivo elegante com proporções de relógio dress, cases ultraslim (sub 10mm), movimento Miyota 9039 e pulseiras de couro perfurado feitas à mão. O Marque Racing é considerado o automático mais fino do mercado em sua categoria. | J51: Patron, Marque Racing, Marque Automatic | K51: https://cdn.sanity.io/images/vxy259ii/production/15bdc873b30deefed241b27a828c5991fb1348b2-1500x1500.png
A52: Alpina | B52: Suíça | C52: Genebra | D52: Pioneira do "Sport Chronograph" e relógios de aviação | E52: {=INDEX('Tabela de faixa de preços'!$A$1:$A$10,MATCH(1,('Tabela de faixa de preços'!$B$1:$B$10<=F52)*('Tabela de faixa de preços'!$C$1:$C$10>=F52),0))} | F52: 8000 | G52: alpinawatches.com | H52: @alpinawatches | I52: Alpina foi fundada em 1883 por Gottlob Hauser, em Genebra, originalmente como uma cooperativa de relojoeiros suíços. Em 1933 lançou o icônico Alpina 4, considerado um marco entre os relógios esportivos por sua robustez (anti-magnético, à prova d'água, anti-choque, em aço inoxidável). A marca é também pioneira na história dos cronógrafos e relógios para pilotos. Após declínio durante a crise do quartzo, foi relançada em 2002 e hoje pertence ao Frédérique Constant Group (parte do Citizen Group), com foco em mergulho, aviação e smartwatches híbridos. [⚠️ verificar] | J52: Alpina 4, Seastrong Diver, Startimer Pilot, Alpiner | K52: https://cdn.shopify.com/s/files/1/0326/7942/8234/files/logo-footer.jpg?v=1718323651
A53: Alsta | B53: USA | C53: Glasgow (sede atual) | D53: Relógio dive icônico do filme Tubarão (1975) | E53: 2 | F53: 4500 | G53: alstawatch.com | H53: @alstawatchcompany | I53: Alsta foi fundada em 1946 em Nova York pela Alstater Watch Co., focada em relógios mecânicos para profissionais e cientistas. Tornou-se famosa pelo Nautoscaph Superautomatic — o relógio dive usado por Richard Dreyfuss como Matt Hooper em "Tubarão" (1975). Após sucumbir à crise do quartzo nos anos 80, foi relançada em 2014/2017 pelo entusiasta escocês Angus MacFadyen, agora sediada em Glasgow. As novas referências mantêm o espírito dos originais com movimentos suíços Sellita SW200-1. | J53: Nautoscaph IV, Superautomatic 2025, Surf n Ski, Motoscaphe | K53: https://alstawatch.com/cdn/shop/files/Alsta-Logo-White-Raster-RGB-v2.png?v=1690206738
A54: Alterum | B54: EUA (fabricado na Suíça) | D54: Microbrand de relógios de design contemporâneo | E54: 1 | F54: 1500 | G54: alterumwatchco.com | H54: @alterumwatches | I54: A Alterum é uma microbrand de relógios de design contemporâneo, com proposta acessível voltada a entusiastas. O nome vem do latim "alterum" (o outro), sugerindo uma identidade ligada à alternativa e à distinção. Os modelos tipicamente combinam design limpo e moderno com movimentos de quartzo e automáticos japoneses, dirigindo-se a quem valoriza estética e bom custo-benefício. Produção em pequenas séries, típica das microbrands. [⚠️ informação pública confiável muito limitada — verificar país/sede, fundador, ano de fundação, coleções específicas e status atual antes de publicar] | J54: Worldtimer (Ref 1, Los Angeles, New York, Horizon) | K54: https://images.squarespace-cdn.com/content/v1/585206dc6b8f5b8b5d87ae6d/ce214d8f-9500-4e11-919d-f56ef3560ccc/Alterum-Logo-8-1.jpg
A55: ALTO Watches | B55: França | C55: Paris | D55: Microbrand de relógios de design contemporâneo | E55: 1 | F55: 1500 | G55: altowatches.com | H55: @altowatches | I55: A ALTO Watches é uma microbrand de relógios de design contemporâneo, com proposta acessível voltada a entusiastas. O nome sugere altura, elevação e ambição, temas comuns em marcas ligadas a aventura e design. Os modelos tipicamente combinam design limpo e moderno com movimentos de quartzo e automáticos japoneses, dirigindo-se a quem valoriza estética e bom custo-benefício. Produção em pequenas séries, típica das microbrands. [⚠️ informação pública confiável muito limitada — verificar país/sede, fundador, ano de fundação, coleções específicas e status atual antes de publicar] | J55: ART 01, ART 02 | K55: https://altowatches.com/wp-content/uploads/2025/01/alto-logo-blanc-package-2025.png
A56: Amida | B56: Suíça | C56: Granges (origem) / Genebra-Meyrin (atual) | D56: Casquette mecânica com display digital por prisma | E56: 3 | F56: 13000 | G56: amida-watches.com | H56: @amida_watches | I56: Amida foi fundada em 1925 em Granges (Suíça) por Joseph Zwahlen, mais tarde mudando-se para Montreux. No Baselworld 1976, em meio à revolução do quartzo, lançou o Digitrend — uma "casquette" mecânica com display digital lateral lido através de um prisma de safira que reflete os discos de hora e minuto a 90°. A marca sucumbiu à crise do quartzo em 1979. Foi relançada em 2024 pelo designer suíço Matthieu Allègre e Clément Meynier (fundador da Depancel) com sede em Meyrin, marcando o 50º aniversário do Digitrend original — agora com módulo desenvolvido in-house sobre o automático Soprod Newton. | J56: Digitrend Steel, Digitrend Black, Digitrend Gold, Digitrend Open Sapphire | K56: https://www.amida-watches.com/cdn/shop/files/logo-black_220x.png?v=1784142313
A57: Ancon | D57: Microbrand de relógios de inspiração náutica | E57: 1 | F57: 1500 | H57: @anconwatches | I57: A Ancon é uma microbrand de relógios de design contemporâneo, com proposta acessível voltada a entusiastas. O nome remete a "âncora" (do grego "ankon"), sugerindo identidade náutica e marítima. Os modelos tipicamente combinam design limpo e moderno com movimentos de quartzo e automáticos japoneses, dirigindo-se a quem valoriza estética e bom custo-benefício. Produção em pequenas séries, típica das microbrands. [⚠️ informação pública confiável muito limitada — verificar país/sede, fundador, ano de fundação, coleções específicas e status atual antes de publicar] | J57: Coleções de design contemporâneo | K57: https://www.seriouswatches.com/cdn/shop/collections/Ancon_150x.jpg?v=1499772833
A58: Andersen Genève | B58: Suíça | C58: Genebra | D58: Mestre da hora do mundo e complicações artísticas | E58: {=INDEX('Tabela de faixa de preços'!$A$1:$A$10,MATCH(1,('Tabela de faixa de preços'!$B$1:$B$10<=F58)*('Tabela de faixa de preços'!$C$1:$C$10>=F58),0))} | F58: 350000 | G58: andersen-geneve.ch | H58: @andersen_geneve | I58: Andersen Genève foi fundada em 1980 pelo dinamarquês Svend Andersen (n. 1942), apelidado de "relojoeiro do impossível" após criar em 1969 o "Bottle Clock" — um relógio inteiro montado dentro de uma garrafa de vidro pelo gargalo. Após uma década no Atelier des Grandes Complications da Patek Philippe, abriu seu ateliê no Quai du Seujet em Genebra. Co-fundou em 1985 a AHCI (Académie Horlogère des Créateurs Indépendants). A marca produz cerca de 50 peças por ano em Genebra e La Chaux-de-Fonds, especializando-se em world timers, jumping hours e calendários perpétuos seculares. | J58: Communication, Tempus Terrae, Montre à Tact, Jumping Hours, Eros
A59: Andersmann | B59: Suíça | C59: Hong Kong (Swiss Made) | D59: Mergulhadores robustos de 3000m em titânio Grade 5 | E59: 3 | F59: 14000 | G59: andersmann.com | H59: @andersmann_watches | I59: Andersmann é uma marca sediada em Hong Kong, criada pelo entusiasta Raymond Chan (o nome remete ao filho do fundador). Apesar da sede asiática, todos os relógios são Swiss Made — montados em Bienne na Suíça com movimentos ETA 2892-A2. O foco é exclusivo em mergulhadores de alta performance: a coleção Deep Ocean atinge 3000m em titânio Grade 5 com lunetas cerâmicas, ao lado das linhas Oceanmaster I e II. Edições limitadas a 100 peças, com testes duplos de pressão (Suíça + laboratório próprio com equipamento Roxer). [⚠️ planilha indicava Suíça — corrigir para HK] | J59: Deep Ocean ANN0913, ANN0982, Oceanmaster I, Oceanmaster II, Bronze ANN0931 | K59: https://oracleoftime.com/wp-content/uploads/2020/06/Andersmann-Logo.jpg
A60: Andreas Strehler | B60: Suíça | C60: Sirnach (Turgóvia) | D60: Relojoeiro independente premiado por engenharia mecânica | E60: {=INDEX('Tabela de faixa de preços'!$A$1:$A$10,MATCH(1,('Tabela de faixa de preços'!$B$1:$B$10<=F60)*('Tabela de faixa de preços'!$C$1:$C$10>=F60),0))} | F60: 670000 | G60: andreasstrehler.ch | H60: @andreasstrehler | I60: Andreas Strehler é um dos mais respeitados relojoeiros independentes da Suíça, baseado em Sirnach. Iniciou sua carreira em 1991 como chefe de prototipagem na Renaud & Papi (manufatura de movimentos onde muitos grandes independentes começaram). Membro da AHCI, é conhecido por seu rigor mecânico e calendários perpétuos seculares de altíssima precisão — seu Lune Exacte tem o calendário lunar mais preciso já feito. Trabalha também como consultor de complicações para outras manufaturas. Peças são únicas ou em edições mínimas. [⚠️ verificar] | J60: Sirius Papillon, Lune Exacte, Cocon, Sauterelle à Lune Perpétuelle
A61: Angelus | B61: Suíça | C61: Le Locle | D61: Marca histórica relançada com cronógrafos esqueletos | E61: {=INDEX('Tabela de faixa de preços'!$A$1:$A$10,MATCH(1,('Tabela de faixa de preços'!$B$1:$B$10<=F61)*('Tabela de faixa de preços'!$C$1:$C$10>=F61),0))} | F61: 220000 | G61: angelus-watches.com | H61: @angeluswatches | I61: Angelus foi fundada em 1891 em Le Locle pelos irmãos Albert e Gustav Stolz, ganhando renome no início do século XX por relógios despertadores e cronógrafos sofisticados — entre eles o Chronodato (primeiro cronógrafo com calendário completo, 1942) e o Tinkler. Após sucumbir à crise do quartzo, a marca ficou hibernando por décadas. Foi relançada em 2011 sob o guarda-chuva da La Joux-Perret (parte do Citizen Group), focada em peças em edição limitada com cronógrafos esqueletos modernos como o U10 Tourbillon Lumière e o U20 Ultra Skeleton Tourbillon. [⚠️ verificar] | J61: U10 Tourbillon Lumière, U20 Ultra Skeleton, U30 Black Tourbillon Skeleton | K61: https://angelus.b-cdn.net/content/uploads/2026/04/09092155/angelus-logo-1.png
A62: Angles | D62: Microbrand de relógios de design contemporâneo | E62: 1 | F62: 1500 | H62: @angleswatches | I62: A Angles é uma microbrand de relógios de design contemporâneo, com proposta acessível voltada a entusiastas. O nome ("ângulos") sugere uma identidade ligada a geometria e design arquitetônico. Os modelos tipicamente combinam design limpo e moderno com movimentos de quartzo e automáticos japoneses, dirigindo-se a quem valoriza estética e bom custo-benefício. Produção em pequenas séries, típica das microbrands. [⚠️ informação pública confiável muito limitada — verificar país/sede, fundador, ano de fundação, coleções específicas e status atual antes de publicar] | J62: Coleções de design contemporâneo | K62: https://angleswatches.com/cdn/shop/files/ANGLES_cf4854de-1cdf-4041-a8e3-d20007e3efdc.png?v=1642060158&width=500
A63: Angular Momentum | B63: Suíça | C63: Berna (Ittigen) | D63: Atelier independente artístico de Martin Pauli | E63: {=INDEX('Tabela de faixa de preços'!$A$1:$A$10,MATCH(1,('Tabela de faixa de preços'!$B$1:$B$10<=F63)*('Tabela de faixa de preços'!$C$1:$C$10>=F63),0))} | F63: 12000 | G63: angularmomentum.com | H63: @angularmomentum | I63: Angular Momentum foi fundada em 1998 em Berna por Martin Pauli, mestre relojoeiro suíço que opera o ateliê junto com sua marca-irmã Manu Propria. A casa é defendidamente independente, produzindo um pequeno volume de peças totalmente feitas à mão (sem CNC) — Pauli já criou mais de 1.000 timepieces únicos para colecionadores ao redor do mundo. Famoso pelos discos giratórios da série ILLUM, pelos cases bronze steampunk Polyphemos, mostradores em laca urushi, miniaturas pintadas e enamel "Émail Lumineuse" que brilha no escuro. Também faz canetas tinteiro com técnica japonesa maki-e. | J63: ILLUM, Polyphemos, Sparrow, Hidden Snake, Hemisphere | K63: https://www.angularmomentum.com/images/angular_logo.gif
A64: Anicorn | B64: Hong Kong | C64: Hong Kong | D64: Estúdio de design com discos rotativos e colaborações | E64: 1 | F64: 4000 | G64: anicorn-watches.com | H64: @anicorn_watches | I64: Anicorn é uma marca de Hong Kong, fundada em 2014 pelo designer gráfico Joe Kwan e o empreendedor Chris Chan. Diferente das marcas tradicionais, a Anicorn tem ADN de estúdio de design — fundindo tipografia, design e mecânica com estética minimalista contemporânea. Famosa pelas séries com discos concêntricos no lugar de ponteiros (Series 000, K452) e por colaborações de impacto: NASA (60º aniversário, 60 peças), Hideo Kojima (SPACE LUDENS) e designers como Hamish Smyth, Jesse Reed (Order) e M/M Paris. Posicionamento próximo ao streetwear, com tiragens limitadas. | J64: Series 000, Series K452, NASA Edition, SPACE LUDENS, Order Sequence | K64: https://www.anicorn-watches.com/cdn/shop/files/Logo_A_672cab4d-91bf-4958-9d75-742a9d6b64d3.png?v=1788849781&width=500
A65: Anoma | B65: Reino Unido | C65: Londres | D65: Cases triangulares lugless inspirados em Charlotte Perriand | E65: {=INDEX('Tabela de faixa de preços'!$A$1:$A$10,MATCH(1,('Tabela de faixa de preços'!$B$1:$B$10<=F65)*('Tabela de faixa de preços'!$C$1:$C$10>=F65),0))} | F65: 11000 | G65: anomawatches.com | H65: @anomawatches | I65: Anoma é uma microbrand independente fundada em Londres por Matteo Violet-Vianello, ex-Sotheby's e ex-A Collected Man. O nome vem de "anomalia" — a marca aposta em design disruptivo, com case triangular lugless de 39mm × 38mm em aço polido, inspirado em uma mesa de café de 1950 desenhada por Charlotte Perriand (movimento orgânico-biomórfico do mid-century). Movimento Sellita SW100 automático, cristal safira moldado no triângulo, pulseira de couro italiano integrada. Lançou em 2024 o A1 First Series (azul), seguido pelo A1 Slate, A1 Optical (op art) e a Core Collection (Abyss, Stone) — agora coleção permanente. | J65: A1 First Series, A1 Slate, A1 Optical, A1 Abyss, A1 Stone | K65: https://anomawatches.com/cdn/shop/files/Anoma_Logo_2023.png?v=1698508490&width=500
A66: Anonimo | B66: Suíça | C66: Florença / La Chaux-de-Fonds | D66: Cases "cushion" característicos com herança de mergulho italiano | E66: {=INDEX('Tabela de faixa de preços'!$A$1:$A$10,MATCH(1,('Tabela de faixa de preços'!$B$1:$B$10<=F66)*('Tabela de faixa de preços'!$C$1:$C$10>=F66),0))} | F66: 15000 | G66: anonimo.com | H66: @anonimo_firenze | I66: Anonimo foi fundada em 1997 em Florença, Itália, pelo ex-comandante da Marinha italiana Dino Zei e pelo industrial Federico Massacesi, herdando o know-how da extinta Officine Panerai italiana após a venda à Richemont. A marca tornou-se conhecida pelos cases "cushion" (almofadados) em aço bronze e pela vocação de tool watches robustos para mergulho e aviação. Em 2013, após dificuldades, foi relançada em parceria com investidores suíços, transferindo a manufatura para La Chaux-de-Fonds, embora mantenha o DNA estético italiano. [⚠️ verificar] | J66: Militare, Nautilo, Epurato, Marlin | K66: https://anonimo.com/cdn/shop/files/ANONIMO_25_years_400x.jpg?v=1658475050
A67: anOrdaim | B67: Escócia | C67: Glasgow | D67: Mostradores em esmalte vitreoso fumé feitos à mão | E67: {=INDEX('Tabela de faixa de preços'!$A$1:$A$10,MATCH(1,('Tabela de faixa de preços'!$B$1:$B$10<=F67)*('Tabela de faixa de preços'!$C$1:$C$10>=F67),0))} | F67: 15000 | G67: anordain.com | H67: @anordainwatches | I67: anOrdain (grafia oficial) foi fundada em 2015 em Glasgow por Lewis Heath, com nome inspirado em Loch an Ordain, um lago remoto nas Highlands escocesas. A marca é uma das poucas no mundo a fazer mostradores em esmalte vitreoso grand feu inteiramente in-house, com um processo de 12 horas e dezenas de cozimentos por peça. O time desenvolveu o primeiro esmalte fumé do mundo (gradiente esfumaçado), uma inovação acidental que se tornou assinatura da casa. A tipografia dos mostradores é inspirada em mapas Ordnance Survey escoceses. A produção é limitada a cerca de 14 mostradores por semana, com lista de espera. [⚠️ grafia correta é anOrdain] | J67: Model 1, Model 2, Model 3 Method, Fabrik Model 1 | K67: https://anordain.com/cdn/shop/files/anordain-header-logo-blue.svg?v=1747402199
A68: Anpassa | B68: Hong Kong | C68: Hong Kong | D68: Relojoaria personalizada e bespoke | E68: {=INDEX('Tabela de faixa de preços'!$A$1:$A$10,MATCH(1,('Tabela de faixa de preços'!$B$1:$B$10<=F68)*('Tabela de faixa de preços'!$C$1:$C$10>=F68),0))} | F68: 8000 | G68: anpassawatch.com | H68: @anpassawatch | I68: Anpassa foi fundada em 2013/2014 em Hong Kong por Gary Ching, ex-fotógrafo profissional que aplicou a ideia de "capturar momentos memoráveis" na relojoaria. O nome vem do sueco "anpassa" (personalizar/ajustar), refletindo o conceito do bespoke: cada peça é única, projetada conforme o pedido do cliente. A marca chegou a desenvolver seu próprio calibre (cal. 1517) em apenas 10 meses. Ching é apaixonado por mostradores artísticos com pedras preciosas, metais e elementos personalizados. Anpassa também atua como mentora educacional, treinando estudantes de relojoaria em Hong Kong. | J68: Designer's Series, peças únicas customizadas | K68: https://static.wixstatic.com/media/5c96d1_e9bc58094f5a41e7a9bf1f861d5ce75f~mv2.png | L68: Site bloqueado – loja anpassaidee.store e site da linha Idée (ideehk.com) não abriram; revisitar com navegador
A69: Anstead | D69: Microbrand de dive watches acessíveis | E69: 2 | F69: 3000 | H69: @ansteadwatches | I69: A Anstead é uma microbrand de relógios de design contemporâneo, com proposta acessível voltada a entusiastas. O nome é de sonoridade britânica, sugerindo identidade ligada ao Reino Unido. A marca é conhecida entre entusiastas por dive watches acessíveis. Os modelos tipicamente combinam design limpo e moderno com movimentos de quartzo e automáticos japoneses, dirigindo-se a quem valoriza estética e bom custo-benefício. Produção em pequenas séries, típica das microbrands. [⚠️ informação pública confiável muito limitada — verificar país/sede, fundador, ano de fundação, coleções específicas e status atual antes de publicar] | J69: Coleções de dive watches | L69: Site bloqueado – ansteadwatches.com recusa leitura automática (robots); revisitar com navegador
A70: Antoine Martin | B70: Suíça | C70: Alpnach (Lago Lucerna) | D70: Calibre Slow Runner com balanço de 24mm a 1Hz | E70: {=INDEX('Tabela de faixa de preços'!$A$1:$A$10,MATCH(1,('Tabela de faixa de preços'!$B$1:$B$10<=F70)*('Tabela de faixa de preços'!$C$1:$C$10>=F70),0))} | F70: 80000 | G70: antoinemartin.ch | H70: @antoinemartin_watches | I70: Antoine Martin é uma manufatura suíça de luxo co-fundada em 2009 pelo mestre relojoeiro alemão Martin Braun (anteriormente proprietário da Martin Braun Uhren, com complicações astronômicas premiadas) e pelo empresário Antoine Meier, com manufatura em Alpnach às margens do Lago Lucerna. A marca tornou-se famosa em 2013 ao lançar o Slow Runner — o primeiro e único relógio do mundo a operar a apenas 7.200 batidas por hora (1 Hertz), com um balanço gigante de 24mm em titânio Grade 3 e espiral em silício. Outras criações notáveis incluem o Quantième Perpétuel à Grand Balancier e o Tourbillon Astronomique. | J70: Slow Runner, Quantième Perpétuel, Tourbillon Astronomique | K70: https://www.antoinemartin.ch/Logo_antoinemartin.png
A71: Antoine Preziuso | B71: Suíça | C71: Genebra | D71: Tourbillons múltiplos e relojoaria independente artesanal | E71: 7 | F71: 90000 | G71: antoinepreziuso.com | H71: @antoinepreziuso | I71: Antoine Preziuso é um relojoeiro independente suíço de origem italiana, baseado em Genebra. Membro da AHCI, formou-se na escola de relojoaria de Genebra e trabalhou na Patek Philippe antes de abrir seu ateliê em 1989. Tornou-se conhecido por suas complicações e especialmente pelo Tourbillon of Tourbillons (TTR-3X), com três tourbillons girando sobre uma plataforma central que também rotaciona — uma das complicações mais espetaculares da relojoaria moderna. Hoje seu filho Florian Preziuso atua na manufatura familiar. [⚠️ verificar] | J71: Tourbillon of Tourbillons (TTR-3X), Chronotourbillon, Tropical | K71: https://r2.watchonista.com/app/uploads/legacy/watchographer/168/profile/csm_logo_antoine_preziuso_c81bb13761-640x320.jpg | L71: Site bloqueado – antoinepreziuso.com recusa leitura automática (robots); revisitar com navegador
A72: Anton Suhanov | B72: Russia | C72: São Petersburgo | D72: Relojoeiro independente de tourbillons triplos e relógios mecânicos avant-garde | E72: 7 | F72: 180000 | G72: anton-suhanov.com | H72: @antonsuhanovwatch | I72: Anton Suhanov é um dos relojoeiros independentes mais celebrados da Rússia, baseado em São Petersburgo. Engenheiro mecânico formado na Universidade Politécnica de São Petersburgo, começou em 2007 trabalhando ao lado de Konstantin Chaykin, eventualmente tornando-se chefe de produção da manufatura. Em 2016 venceu o Young Talent Competition de F.P. Journe com seu Black Clock (primeiro relógio de mesa russo com tourbillon de três eixos). Fundou sua própria marca em 2018 e tornou-se candidato AHCI. Em 2025 ganhou o "Horological Revelation Prize" no GPHG. Conhecido por relógios de mesa com tourbillons triplos (Pharos, Lotus) e wristwatches inovadores como o Racer Jumping Hour GMT e o Chronotope. | J72: Racer Jumping Hour GMT, Chronotope, Flamingo, Pharos, Lotus | K72: https://anton-suhanov.com/local/templates/suhanov/img/logo/logo.svg
A73: Anura Rafael | D73: Microbrand de relógios de design contemporâneo | E73: 1 | F73: 1500 | H73: @anurarafael | I73: A Anura Rafael é uma microbrand de relógios de design contemporâneo, com proposta acessível voltada a entusiastas. O nome combina sonoridades que sugerem identidade autoral, possivelmente ligada ao nome do fundador. Os modelos tipicamente combinam design limpo e moderno com movimentos de quartzo e automáticos japoneses, dirigindo-se a quem valoriza estética e bom custo-benefício. Produção em pequenas séries, típica das microbrands. [⚠️ informação pública confiável muito limitada — verificar país/sede, fundador, ano de fundação, coleções específicas e status atual antes de publicar] | J73: Coleções de design contemporâneo
A74: Aonic | D74: Microbrand de relógios de design contemporâneo | E74: 1 | F74: 1500 | H74: @aonicwatches | I74: A Aonic é uma microbrand de relógios de design contemporâneo, com proposta acessível voltada a entusiastas. O nome de sonoridade moderna e tecnológica sugere identidade ligada a design contemporâneo. Os modelos tipicamente combinam design limpo e moderno com movimentos de quartzo e automáticos japoneses, dirigindo-se a quem valoriza estética e bom custo-benefício. Produção em pequenas séries, típica das microbrands. [⚠️ informação pública confiável muito limitada — verificar país/sede, fundador, ano de fundação, coleções específicas e status atual antes de publicar] | J74: Coleções de design contemporâneo | K74: https://www.aeonic-watches.com/wp-content/themes/aeonic-watches/_images/aeonic-logo.1696767676.svg
A75: Aquadive | B75: Áustria | C75: Origem 1962 / Suíça-Alemanha (atual) | D75: Mergulhadores Bathyscaphe com 1000m de resistência | E75: {=INDEX('Tabela de faixa de preços'!$A$1:$A$10,MATCH(1,('Tabela de faixa de preços'!$B$1:$B$10<=F75)*('Tabela de faixa de preços'!$C$1:$C$10>=F75),0))} | F75: 11000 | G75: aquadive.com | H75: @aquadive_watches | I75: Aquadive foi fundada em 1962, dedicada exclusivamente a relógios de mergulho desde o início — algo raro para a época. Suas peças tornaram-se padrão entre mergulhadores profissionais e foram endossadas pelo astronauta da Mercury Scott Carpenter. O Aquadive Model 50 com manômetro de profundidade Bourdon e o Aquadive 1000 (resistente a 1.000m) são icônicos. Sucumbiu à crise do quartzo nos anos 80 e foi relançada em 2011 por Rick Marei, sob o Synchron Group (mesmo grupo da Doxa). Hoje os cases são CNC-fresados na Alemanha em aço cirúrgico 316L e bronze, e a montagem é feita na Suíça com movimentos ETA. [⚠️ planilha indicava Áustria — verificar] | J75: Bathyscaphe 100, Bathyscaphe 100 GMT, Bathysphere 3000 | K75: https://aquadive.com/wp-content/uploads/2025/08/Aquadive-logo.jpg | L75: Parcial – loja oficial shop.synchronwatches.com, sitemap e products.json de aquadive.com não abriram; revisitar com navegador
A76: Aquanautic | B76: Suíça | C76: Genebra | D76: Cases tonneau náuticos com componentes intercambiáveis | E76: {=INDEX('Tabela de faixa de preços'!$A$1:$A$10,MATCH(1,('Tabela de faixa de preços'!$B$1:$B$10<=F76)*('Tabela de faixa de preços'!$C$1:$C$10>=F76),0))} | F76: 13000 | G76: aquanautic.com | H76: @aquanautic_swiss | I76: Aquanautic foi estabelecida em 2002 em Genebra pela Raymeyer & Co. SA, com sede no histórico Molard Square Clock Tower — onde os sinos da torre antigamente anunciavam a chegada de barcos. Inteiramente Swiss Made, é vendida em mais de 30 países. A assinatura da marca são os cases tonneau com forte inspiração náutica e o sistema de componentes intercambiáveis (lunetas, máscaras, pulseiras), permitindo personalização fácil. Modelos icônicos como King Cuda e Bara Cuda usam movimentos automáticos Valjoux 7750 e ETA, com mergulhadores resistentes até 500m. | J76: King Cuda, Bara Cuda, Princess Cuda, King Sub Commander, Hydrocraft | K76: https://piazo.jp/assets/base/img/content/top_brand/aquanautic.png | L76: Site bloqueado – aquanautic.com recusa leitura automática (robots); revisitar com navegador
A77: Aquastar | B77: Suíça | C77: Genebra | D77: Marca histórica de mergulho relançada com Deepstar | E77: {=INDEX('Tabela de faixa de preços'!$A$1:$A$10,MATCH(1,('Tabela de faixa de preços'!$B$1:$B$10<=F77)*('Tabela de faixa de preços'!$C$1:$C$10>=F77),0))} | F77: 15000 | G77: aquastar.com | H77: @aquastar_watches | I77: Aquastar foi fundada em 1962 em Genebra pelo francês Frédéric Robert, depois de anos liderando a JeanRichard SA. A marca rapidamente se destacou na relojoaria de mergulho, com inovações como o cronógrafo Deepstar (1962) — um dos primeiros cronógrafos voltados ao mergulho — e o Benthos. Após declinar durante a crise do quartzo, foi relançada em 2020 reproduzindo fielmente o icônico Deepstar com movimento moderno. É hoje uma das referências entre os colecionadores de relógios dive vintage. [⚠️ verificar] | J77: Deepstar, Benthos, Model 60 | K77: https://aquastar.ch/wp-content/uploads/2025/10/logo-6-1.png | M77: G aponta aquastar.com, que é de frutos do mar; o site oficial é aquastar.ch.
A78: Aquatrident | B78: Hong Kong | C78: Hong Kong | D78: Mergulhadores acessíveis em fibra de carbono, opala e meteorito | E78: 1 | F78: 1800 | G78: aquatrident.com | H78: @aquatridentwatch | I78: Aquatrident é uma marca de Hong Kong cujo nome combina "água" com "tridente" — em referência à mitologia do oceano. A marca produz mergulhadores acessíveis (a partir de ~€300), com foco em materiais distintivos: fibra de carbono, opala, bronze e meteorito. Movimentos japoneses TMI NH35 e cases em aço 316L marine grade. As coleções incluem Ichthyosaur (500m), Ocean, Shark, Neptune, Jaws, Helmsman, Atlantis e Mariner — todas evocando vida aquática. | J78: Ichthyosaur, Ocean, Shark, Neptune, Jaws | L78: Site bloqueado – aquatrident.com recusa leitura automática (robots); modelos listados pelos títulos das páginas indexadas; revisitar com navegador
A79: Arach | D79: Microbrand de relógios de design contemporâneo | E79: 1 | F79: 1500 | H79: @arachwatches | I79: A Arach é uma microbrand de relógios de design contemporâneo, com proposta acessível voltada a entusiastas. O nome remete a "aracnídeo", sugerindo uma identidade visual ligada a formas orgânicas ou estrutura em teia. Os modelos tipicamente combinam design limpo e moderno com movimentos de quartzo e automáticos japoneses, dirigindo-se a quem valoriza estética e bom custo-benefício. Produção em pequenas séries, típica das microbrands. [⚠️ informação pública confiável muito limitada — verificar país/sede, fundador, ano de fundação, coleções específicas e status atual antes de publicar] | J79: Coleções de design contemporâneo | K79: https://cdn.watchtraderhub.com/brands/9e60f538-4c40-4885-b15e-cf4afb506fae/logo-1778437046377-BM3vSxsbph.webp
A80: Aramar Watch Co. | D80: Microbrand de relógios de inspiração náutica | E80: 1 | F80: 1500 | H80: @aramarwatches | I80: A Aramar Watch Co. é uma microbrand de relógios de design contemporâneo, com proposta acessível voltada a entusiastas. O nome combina sonoridades ibéricas e remete ao mar, sugerindo identidade náutica. Os modelos tipicamente combinam design limpo e moderno com movimentos de quartzo e automáticos japoneses, dirigindo-se a quem valoriza estética e bom custo-benefício. Produção em pequenas séries, típica das microbrands. [⚠️ informação pública confiável muito limitada — verificar país/sede, fundador, ano de fundação, coleções específicas e status atual antes de publicar] | J80: Coleções de design contemporâneo | L80: Site bloqueado – aramar.nl e aramarwatches.com recusam leitura automática (robots); revisitar com navegador
A81: Arcadia Watches | B81: Suíça | C81: Genebra (origem Fleurier) | D81: Marca histórica Fleurier de 1858 relançada por Maison Bunter | E81: 5 | F81: 25000 | G81: arcadia-watches.com | H81: @arcadiawatches | I81: Arcadia Watches é uma marca suíça de relógios de luxo fundada em 1858 em Fleurier (cantão de Neuchâtel) pelo relojoeiro Jules-Samuel Jequier — ex-Bovet — como carro-chefe da Fleurier Watch Company, ao lado de marcas contemporâneas como Breitling e Rolex. A marca foi pioneira na exportação para a China e América do Sul. Sucumbiu em 1968 com a chegada do quartzo. Foi relançada em 2007 por Claude Sanz, presidente da Maison Bunter (especialista em alta cravação e complicações em Genebra), e o primeiro novo Arcadia — o cronógrafo mecânico AC01 — saiu em 2010. [⚠️ verificar; existe outra marca homônima americana de field watches] | J81: AC01, modelos contemporâneos com complicações | K81: https://en.worldtempus.com/sites/default/files/styles/brand_logo_1x/public/2023-12/design_sans_titre_50.png?itok=EFjSGT91
A82: Arcaido | D82: Microbrand de relógios de design contemporâneo | E82: 1 | F82: 1500 | H82: @arcaidowatches | I82: A Arcaido é uma microbrand de relógios de design contemporâneo, com proposta acessível voltada a entusiastas. O nome de sonoridade latina remete a "arcaico", sugerindo identidade ligada a herança e tradição. Os modelos tipicamente combinam design limpo e moderno com movimentos de quartzo e automáticos japoneses, dirigindo-se a quem valoriza estética e bom custo-benefício. Produção em pequenas séries, típica das microbrands. [⚠️ informação pública confiável muito limitada — verificar país/sede, fundador, ano de fundação, coleções específicas e status atual antes de publicar] | J82: Coleções de design contemporâneo | L82: Site bloqueado – arcaido.com recusa leitura automática (robots); revisitar com navegador
A83: Arcanaut | B83: Dinamarca | C83: Copenhague | D83: Mostradores em meteorito, raku e materiais experimentais | E83: {=INDEX('Tabela de faixa de preços'!$A$1:$A$10,MATCH(1,('Tabela de faixa de preços'!$B$1:$B$10<=F83)*('Tabela de faixa de preços'!$C$1:$C$10>=F83),0))} | F83: 24000 | G83: arcanaut.watch | H83: @arcanautwatches | I83: Arcanaut é uma microbrand dinamarquesa fundada por Anders Brandt e James Thompson em Copenhague. A marca é conhecida pelos mostradores experimentais — meteorito Muonionalusta, raku (cerâmica japonesa craquelada), Lichtenberg (figuras de descarga elétrica em madeira), e outros materiais incomuns. Usa caixas modernas em titânio e movimentos suíços La Joux-Perret. Cada peça é única dentro de pequenas edições, com forte apelo entre colecionadores que valorizam materiais raros e estética artística. [⚠️ verificar] | J83: Arc II Meteorite, Arc II Raku, Arc II Lichtenberg | K83: https://arcanaut.watch/cdn/shop/files/Arcanaut_logo_512_px_wide_bd05962a-6bc5-428a-88c6-1a071940033d.png?v=1676033516&width=512
A84: Archetype | B84: USA | C84: EUA | D84: Esqueletos automáticos com mostradores skeletonizados | E84: {=INDEX('Tabela de faixa de preços'!$A$1:$A$10,MATCH(1,('Tabela de faixa de preços'!$B$1:$B$10<=F84)*('Tabela de faixa de preços'!$C$1:$C$10>=F84),0))} | F84: 2500 | G84: archetypewatches.com | H84: @archetypewatches | I84: Archetype é uma marca americana especializada em relógios mecânicos esqueletizados — todos automáticos, alimentados pelo movimento do braço (sem necessidade de bateria). A marca aposta em mostradores skeleton com aberturas que revelam o movimento, em uma estética que combina elementos contemporâneos e clássicos. As coleções incluem o Blackhawk Automatic (com complicação big date e calendário, inspirado em pilot watches vintage), Archer Automatic (skeletonizado), além de modelos com discos guilhochê e indicador dia/noite. | J84: Blackhawk Automatic, Archer Automatic, Pure | K84: https://www.archetypewatches.com/cdn/shop/files/Archetype-logo-rg_x45@2x.png?v=1614806788 | M84: J cita a linha 'Pure', que não foi encontrada em nenhuma fonte (o catálogo oficial tem 49 relógios e nenhum 'Pure').
A85: Archimede | B85: Alemanha | C85: Pforzheim | D85: Pilot watches alemães com fabricação Ickler | E85: {=INDEX('Tabela de faixa de preços'!$A$1:$A$10,MATCH(1,('Tabela de faixa de preços'!$B$1:$B$10<=F85)*('Tabela de faixa de preços'!$C$1:$C$10>=F85),0))} | F85: 3500 | G85: archimede-watches.com | H85: @archimede_watches | I85: Archimede é uma marca alemã sediada em Pforzheim, criada pela ICKLER GmbH, fabricante histórica de cases de relógio fundada em 1924. A família Ickler produz cases para muitas marcas alemãs renomadas — Stowa, Damasko e outras — e usa esse know-how em sua linha própria Archimede, focada em pilot watches no estilo Flieger clássico (Tipo A e Tipo B). Movimentos ETA e Sellita, com excelente relação custo-benefício na categoria pilot. Os cases são todos fabricados internamente em Pforzheim. [⚠️ verificar] | J85: Pilot 42, Pilot 39, Outdoor Antarctica, Klassik | K85: https://www.archimede-watches.com/media/b9/bf/14/1752737109/archimede_logo_website_%281%29.jpg?ts=1752737109
A86: ARC-TIC | D86: Microbrand de relógios de temática polar/exploração | E86: 2 | F86: 3000 | H86: @arctic.watches | I86: A ARC-TIC é uma microbrand de relógios de design contemporâneo, com proposta acessível voltada a entusiastas. O nome remete ao Ártico e ao "tique-taque", sugerindo identidade ligada a frio extremo, exploração polar e resistência. Os modelos tipicamente combinam design limpo e moderno com movimentos de quartzo e automáticos japoneses, dirigindo-se a quem valoriza estética e bom custo-benefício. Produção em pequenas séries, típica das microbrands. [⚠️ informação pública confiável muito limitada — verificar país/sede, fundador, ano de fundação, coleções específicas e status atual antes de publicar] | J86: Coleções de design contemporâneo | K86: http://static1.squarespace.com/static/54e612f8e4b0072e73722927/t/54ec7837e4b003ce1bdf10d1/1424783416832/arctic+logo2.jpg?format=1500w | M86: B/C/G vazios: é da Islândia, irmã da JS Watch Co., site arc-tic.com. I e J são genéricos (I fala em automáticos japoneses e não cita a Islândia).
A87: Arctos | B87: Alemanha | C87: Pforzheim | D87: Apresentou o primeiro relógio de pulso a quartzo da Alemanha (1971) | E87: 2 | F87: 4000 | G87: arctos-elite.de | H87: @arctoswatches | I87: Em 1º de abril de 1923, o comerciante Philipp Weber e o relojoeiro Jakob Aeschbach fundaram a Weber & Aeschbach em Pforzheim, com um objetivo modesto: montar relógios de bolso e de pulso. O negócio cresceu rápido — em 1928 já produzia 260 movimentos por dia — e Weber decidiu criar marca própria, registrada em 1924 com o nome ARCTOS, do grego para a constelação da Ursa Maior. A fábrica foi destruída nos bombardeios da Segunda Guerra e reconstruída em 1947, quando passou a se chamar Arctos-Uhrenfabrik Philipp Weber. Vieram os anos de ouro: em 1956 a marca apresentou na Feira de Hannover o "Arctos Horometer", um relógio de hora mundial com calibres automáticos Felsa; a linha Arctos Elite foi criada para competir de igual para igual com as marcas suíças nas melhores relojoarias alemãs. Weber morreu em 1962, aos 72 anos, e os jornais alemães encheram páginas de homenagens ao pioneiro de Pforzheim. Seu filho Werner assumiu — e em 11 de fevereiro de 1971 protagonizou o momento mais sensacional da história da casa, ao apresentar à imprensa o protótipo do primeiro relógio de pulso a quartzo fabricado na Alemanha. A Arctos também se tornou equipamento oficial da OTAN e das Forças Armadas alemãs, sob número de suprimento próprio. A empresa original sucumbiu em 1994 à enxurrada de relógios digitais baratos. Em 2004 a marca foi reerguida como ARCTOS Präzisionsuhren, dirigindo-se a quem valoriza a herança relojoeira de Pforzheim e a estética militar alemã. [⚠️ a Arctos relançada difere da histórica e não é mais fabricada em Pforzheim — verificar] | J87: Arctos Elite, Horometer, coleções militares | K87: https://img.watcharc.org/VxK6vgYg7PluOwd5GGXVsPAyTTtP-AWUOG214zDVL0E/dpr:2/f:webp/rs:fit:300:200/plain/s3://watcharc/logo/arctos.png | L87: Site bloqueado – arctos-elite.de (robots; também o antigo arctos.info); revisitar com navegador
A88: Arcturus | B88: Cingapura | C88: Cingapura | D88: Microbrand asiática com nome da estrela Arcturus | E88: 2 | F88: 3000 | H88: @arcturuswatches | I88: A Arcturus é uma microbrand de Cingapura cujo nome vem de Arcturus — a estrela mais brilhante do hemisfério celeste norte, na constelação de Boieiro, historicamente usada como referência de navegação. A identidade astronômica e de orientação permeia a marca. Os modelos tipicamente combinam design contemporâneo com movimentos automáticos japoneses (Seiko/Miyota), cristal de safira e bom acabamento a preços acessíveis, dirigindo-se a entusiastas do vibrante ecossistema de microbrands do Sudeste Asiático. Produção em pequenas séries. [⚠️ informação pública confiável limitada — verificar fundador, ano de fundação, coleções específicas e status atual antes de publicar] | J88: Coleções de design contemporâneo | M88: G vazio: o site oficial é arcturuswatches.sg (arcturuswatches.com é um site de apostas, não é a marca). J genérico ('Coleções de design contemporâneo').
A89: Ardío | B89: USA | C89: Pensilvânia (Luzerne) | D89: Microbrand boutique com dive watches regulados à mão | E89: 1 | F89: 2800 | G89: ardiowatches.com | H89: @ardiowatches | I89: ARDIO é uma marca boutique americana da Pensilvânia, fundada por Ron Oley — o nome vem de "ardent" (ardente), refletindo paixão e devoção. Seu primeiro relógio, o Caribe, levou mais de 3 anos de desenvolvimento, com cada componente projetado do zero. Cada peça é triplamente testada e regulada à mão nos EUA antes do envio. Edições limitadas a 300 peças por cor, com movimento Miyota 9039 high-beat, cristal safira duplo-domo, lume BGW9 e 200m de resistência (~$525). | J89: Caribe (Light Blue, Gauge Brass, Isotope Green, Gilded Black, Sunrise Orange) | K89: https://ardiowatches.com/cdn/shop/files/Text_Logo_Rev3.png?v=1680238664&width=500
A90: Arethusa | B90: USA | C90: Durham (Carolina do Norte) | D90: Tool watches de viagem com bezel world time | E90: 1 | F90: 2000 | G90: arethusawatch.com | H90: @arethusawatches | I90: Arethusa Watch Co. é uma microbrand americana fundada pelo engenheiro mecânico Ethan Stansbury (formado em Duke). O nome homenageia o HMS Arethusa, cruzador leve da Marinha Real Britânica em que seu avô Cyril B. Stansbury serviu como Petty Supply Officer durante toda a Segunda Guerra — o navio participou de Dunquerque, Malta e do Dia D. O modelo principal é o World Diver: um mergulhador de viagem com 200m, movimento Seiko NH35A, bezel cerâmico "world time" inspirado nos freedivers jet-set dos anos 60 e opção de mostrador em carbono forjado. | J90: World Diver (Carbon, Admiral Blue, Instruments Black) | K90: https://static.wixstatic.com/media/1c68f9_7d84ad923a8c42579df51c79d01fa397~mv2.png
A91: Aristo | B91: Alemanha | C91: Pforzheim | D91: Pilot watches alemães tradição Vollmer | E91: {=INDEX('Tabela de faixa de preços'!$A$1:$A$10,MATCH(1,('Tabela de faixa de preços'!$B$1:$B$10<=F91)*('Tabela de faixa de preços'!$C$1:$C$10>=F91),0))} | F91: 3200 | G91: aristo-uhren.de | H91: @aristo_watches | I91: Aristo é uma marca alemã de Pforzheim fundada em 1907 pelo relojoeiro Julius Epple; o nome Aristo foi adotado nos anos 1920 e registrado em 1936. Em 1998 Hansjörg Vollmer assumiu a marca e, em 2005, uniu-a à fabricante de pulseiras metálicas Ernst Vollmer (fundada em 1922), formando a Aristo Vollmer GmbH. É conhecida por pilot watches (Flieger) clássicos, relógios Bauhaus e séries com movimentos antigos recondicionados (Longines Record, AS 2072, Durowe, PUW), além de movimentos suíços Sellita, ETA e Ronda. O mesmo grupo fabrica as marcas Messerschmitt, Erbprinz, Vollmer e Jacques Etoile. | J91: Aristo 3H, Flieger 47, Bauhaus, Vintage Erbstück | K91: https://www.aristo-uhren.de/images/layout/branding.svg
A92: Arken | B92: Reino Unido | C92: Birmingham | D92: Tool watches em titânio com módulo GMT próprio | E92: 2 | F92: 4000 | G92: arken.uk | H92: @arkenwatches | I92: Arken Watch Company foi fundada em outubro de 2020 pelo autodidata Kenneth Lam, que veio do universo de mods de Seiko. O lema em latim "Aut Viam Inveniam Aut Faciam" (acharei um caminho ou farei um) define a marca. O primeiro modelo, Instrumentum (2021), era um diver integrado em titânio Grade 2 com coating anti-riscos, 300m e preço agressivo — esgotou rápido. O Alterum (2023) trouxe um módulo dual-time 12h próprio sobre o Miyota 9015, algo inédito na faixa de preço (~£600). Vendas esgotam em minutos; compradores originais formam o "Arken Armoury" com acesso a edições exclusivas. | J92: Instrumentum, Alterum | L92: Site bloqueado – arken.uk (Squarespace) não abre para leitura automática (permissão negada à ferramenta); revisitar com navegador
A93: Arlanch | D93: Microbrand de relógios de design contemporâneo | E93: 1 | F93: 1500 | H93: @arlanchwatches | I93: A Arlanch é uma microbrand de relógios de design contemporâneo, com proposta acessível voltada a entusiastas. O nome de sonoridade europeia sugere identidade ligada a herança regional. Os modelos tipicamente combinam design limpo e moderno com movimentos de quartzo e automáticos japoneses, dirigindo-se a quem valoriza estética e bom custo-benefício. Produção em pequenas séries, típica das microbrands. [⚠️ informação pública confiável muito limitada — verificar país/sede, fundador, ano de fundação, coleções específicas e status atual antes de publicar] | J93: Coleções de design contemporâneo | L93: Site bloqueado – arlanch.se (endereço que não está na coluna G) não abre para leitura automática (redirecionamento em laço http/https); revisitar com navegador | M93: B/C/G vazios: marca sueca do designer Gabriel Arlanch, site arlanch.se. D/I/J genéricos.
A94: Armand Nicolet | B94: Suíça | C94: Tramelan | D94: Relógios com movimentos vintage NOS restaurados | E94: {=INDEX('Tabela de faixa de preços'!$A$1:$A$10,MATCH(1,('Tabela de faixa de preços'!$B$1:$B$10<=F94)*('Tabela de faixa de preços'!$C$1:$C$10>=F94),0))} | F94: 16000 | G94: armandnicolet.com | H94: @armandnicolet | I94: Armand Nicolet é uma manufatura suíça de Tramelan (Jura bernês), fundada em 1902 por Armand Nicolet, filho de relojoeiro. A marca ficou conhecida entre colecionadores pela série de edições limitadas usando movimentos NOS (new old stock) das décadas de 1950-70, estocados pela família e restaurados um a um — caso dos calibres da coleção L07/L09. Também produz linhas contemporâneas como M02, JS9 e a feminina. Desde 2017 pertence ao grupo italiano de Rolando Braga. [⚠️ verificar] | J94: L07, L09 (NOS), M02-4, JS9, MH8 | L94: Parcial – armandnicolet.com: sitemap.xml, página /collection e PDFs da Resource Hub não abrem para leitura automática (Wix); revisitar com navegador | M94: I diz fundada em 1902; as fontes dizem 1875. J cita 'MH8', que não foi encontrado.
A95: Armando Legin | D95: Marca autoral de relógios de nicho | E95: 2 | F95: 3000 | H95: @armandolegin | I95: A Armando Legin é uma microbrand de relógios de design contemporâneo, com proposta acessível voltada a entusiastas. O nome próprio sugere uma marca autoral, batizada com o nome do fundador. Os modelos tipicamente combinam design limpo e moderno com movimentos de quartzo e automáticos japoneses, dirigindo-se a quem valoriza estética e bom custo-benefício. Produção em pequenas séries, típica das microbrands. [⚠️ informação pública confiável muito limitada — verificar país/sede, fundador, ano de fundação, coleções específicas e status atual antes de publicar] | J95: Coleções de design contemporâneo | K95: https://www.armandolegin.com/images/logo3.png | M95: B/C vazios: Eslovênia (Ljubljana), montagem em Zurique. D/I/J falam de microbrand acessível com movimentos japoneses — errado: é alta relojoaria (base Vaucher, cerca de US$ 17.900). F (3000) muito baixo. G vazio: armandolegin.com. H: o Instagram oficial é @armandoleginofficial.
A96: Armida | B96: Hong Kong | C96: Hong Kong | D96: Tool divers robustos com excelente custo-benefício | E96: 1 | F96: 2500 | G96: armidawatches.com | H96: @armidawatches | I96: Armida é uma marca de propriedade austríaca sediada em Hong Kong, criada por entusiastas com mais de 15 anos de coleção de relógios e mergulho. Especializa-se em tool divers robustos e legíveis a preços muito competitivos ($350-$700), com movimentos suíços ETA/Sellita ou japoneses Seiko/Miyota. O A1 (45mm, 1000m) foi o primeiro modelo; o A1 em latão (brass) tornou-se cult pela acessibilidade no segmento. Todos os modelos passam por testes intensivos subaquáticos antes da produção. Fabricação pela Fullswing, mesma fábrica de outras microbrands respeitadas. | J96: A1 (1000m), A2 Milsub, A7, A8 Brass, A11 (36mm) | K96: https://armidawatches.com/ws/media-library/4744f0c1f425489df4c8ed52ad7f83ce/armida-logo.png | L96: Parcial – armidawatches.com: as páginas de produto da loja (Ecwid, endereços com #!) não abrem para leitura automática; revisitar com navegador | M96: I diz 'propriedade austríaca sediada em Hong Kong'; o WatchPatrol indica China.
A97: Armin Strom | B97: Suíça | C97: Biel/Bienne | D97: Manufatura de resonance e esqueletização moderna | E97: {=INDEX('Tabela de faixa de preços'!$A$1:$A$10,MATCH(1,('Tabela de faixa de preços'!$B$1:$B$10<=F97)*('Tabela de faixa de preços'!$C$1:$C$10>=F97),0))} | F97: 370000 | G97: arminstrom.com | H97: @arminstrom | I97: Armin Strom nasceu do trabalho do relojoeiro homônimo de Burgdorf, mestre da esqueletização à mão desde os anos 1960 (recordista Guinness do menor relógio esqueletizado à mão). Em 2009 a marca tornou-se manufatura completa em Biel/Bienne sob Claude Greisler e Serge Michel, com calibres 100% in-house. É hoje referência mundial em relógios de ressonância — o Mirrored Force Resonance (2016) usa dois balanços acoplados por uma mola patenteada, melhorando a precisão. Coleções: Resonance, Gravity Equal Force, Tribute, Dual Time. [⚠️ verificar] | J97: Mirrored Force Resonance, Gravity Equal Force, Dual Time Resonance, Orbit | K97: https://en.worldtempus.com/sites/default/files/media/wysiwyg/12_1023_AS_Logo_6.jpg
A98: Armitron | B98: USA | C98: Nova York (Long Island) | D98: Quartzo e digitais acessíveis desde 1975 | E98: 1 | F98: 300 | G98: armitron.com | H98: @armitronwatches | I98: Armitron é uma marca americana fundada em 1956 (relógios sob a marca desde 1975) pela E. Gluck Corporation, de Eugen Gluck, sediada em Nova York. Tornou-se um dos maiores nomes de relógios acessíveis dos EUA, popularizando digitais LED/LCD nos anos 70-80 e quartzos analógicos vendidos em grandes varejistas. Os retrô digitais da linha Griffy/Adventure ganharam status cult recentemente. Permanece empresa familiar independente. [⚠️ verificar] | J98: Griffy, Adventure Digital, All-Sport, Dress Quartz | K98: https://iconape.com/armitron-4490-logo-icon-svg-png.html | M98: I diz fundada em 1956 (essa data é da E. Gluck; a marca Armitron é de 1975). J 'Dress Quartz' é genérico.
A99: Armourlite | B99: USA | C99: Flórida | D99: Relógios com iluminação por trítio T100 | E99: 1 | F99: 2500 | G99: armourlite.com | H99: @armourlitewatches | I99: ArmourLite é uma marca americana fundada em 2007, especializada em relógios táticos e profissionais com iluminação por tubos de trítio (T100 — os mais brilhantes da categoria), que brilham por até 25 anos sem carga solar ou bateria. A marca-irmã Isobrite amplia a linha com casos em policarbonato ultra-resistente. Público-alvo: militares, policiais, bombeiros e mergulhadores profissionais. Vidros de safira endurecidos e resistência de até 200m. [⚠️ verificar] | J99: Isobrite T100, Officer Series, Caliber Series | K99: https://www.opticsplanet.com/i/200-200-ffffff/opplanet-armourlite-brand-logo-july-2014.jpg | L99: Parcial – armourlite.com: o leitor automático não traz os produtos (página montada por JavaScript) e muitas páginas internas dão erro; revisitar com navegador
A100: Arnold & Son | B100: Suíça | C100: La Chaux-de-Fonds | D100: Alta relojoaria com herança inglesa de cronometria marítima | E100: {=INDEX('Tabela de faixa de preços'!$A$1:$A$10,MATCH(1,('Tabela de faixa de preços'!$B$1:$B$10<=F100)*('Tabela de faixa de preços'!$C$1:$C$10>=F100),0))} | F100: 90000 | G100: arnoldandson.com | H100: @arnoldandson | I100: Arnold & Son homenageia John Arnold (1736-1799), lendário relojoeiro inglês pioneiro dos cronômetros marítimos e amigo de Abraham-Louis Breguet — a quem forneceu inovações em espirais e escapes. A marca moderna foi estabelecida em 1995 em La Chaux-de-Fonds e hoje pertence ao grupo Citizen (via La Joux-Perret, que fabrica seus calibres manufatura). Especializa-se em complicações com estética inglesa do século XVIII: true beat (segundos mortos), tourbillons, luas gigantes e mostradores em guilloché. Coleções Instrument e Royal. [⚠️ verificar] | J100: True Beat TB88, Ultrathin Tourbillon UTTE, HM Perpetual Moon, Nebula, Longitude | K100: https://en.worldtempus.com/sites/default/files/styles/brand_logo_1x/public/media/brand/arnold-et-son/logo_fond_blanc_arnoldson.jpg?itok=6uZz5Zu6
...

Sheet Planilha1
C1: Marca
A2: Aaron BECSEI | aaronbecseiatelier | C2: 1776 Atelier
A3: ABINGER® | abingerwatches | C3: 2CAN
C4: 2LMX WATCHES
A5: ADDIESDIVE® | addiesdivewatches | C5: 3H Italia
A6: AEROTEC Watches | aerotecwatches | C6: 47 Zero
A7: AGELOCER ORIGINAL | agelocer_official | C7: 4N Watches
A8: ALEXANDRE MARTIN | alexandre.martin.watches | C8: 666 Barcelona
A9: Alterumwatchco | alterumwatchcompany | C9: 6B Watches
A10: Apiar | apiaruk | C10: 88 Rue Du Rhone
A11: Area Nostalgia | areanostalgiawatches | C11: A. Lange & Söhne
A12: Aubert & Ramel | aubert.ramel | C12: A. Manzoni & Fils
A13: Auriva Watches Montres Premium | aurivawatches | C13: AATOS
A14: Baltany watches | baltany_watches | C14: Abingdon
A15: Baume Watches | baumewatches | C15: About Vintage
A16: Blessington Watches | blessington.watches | C16: Accutron
... A24: D1 Milano | d1milano | C24: Aesop
C25: Aether
A26: De Marquee | demarqueewatch | C26: Aethia
A27: Delhi Watch Company | delhiwatchcompany | C27: Airain
A28: Diatom Watches | diatomwatches | C28: Aision
A29: echo/neutra | echo_neutra | C29: Aittokoski Timecrafts Fractalis
A30: EDIFICE OFFICIAL | casioedifice_sg | C30: Akerfalk
A31: EI8HT | ei8ht_watches | C31: Akhor
A32: Elgé Watches | elge_fh | C32: Akrivia
C33: Akrone
A34: EONIQ Watches | Designed & Made in HK | eoniqatelier | C34: Akura
A35: Forward Watch Co. | forwardwatchco | C35: Alain Silberstein
A36: Fukushima Watch Company | fukushima_watch.co | C36: Albert Riele
A37: Galo Watches | galowatches | C37: Albishorn
A38: Grandeur | grandeur | C38: Alcadus
A39: GRØNE Oldenzaal | groneoldenzaal | C39: Alchemists
A40: GUSTAVE & cie | gustave_et_cie | C40: Alessandro Baldieri
A41: Harriot 해리엇 | Korean Watch | harriotwatches | C41: Alessandro Staffetta (AS)
A42: Havid Nagan®️ | havidnagan | C42: Alex Benlo
A43: HGP Watches | hgp_hommes_grenouilles_paris | C43: Alexander James
A44: hodinkee | hodinkee | C44: Alexander Shorokhoff
C45: Alexandre Meerson
C46: Alexis Garin
C47: AleXora
A48: J.T. Winnerl | j.t._winnerl | C48: Alfex
A49: Jean Vernier | Relógios | jeanvernier | C49: Alfred Rochat & Fils
A50: Jiro Katayama | jiro.katayama | C50: Allemano
A51: Kintoshi Kyoto | kintoshikyoto_official | C51: Alludens
A52: KIWAME TOKYO Asakusa | kiwametokyo | C52: Alpina
A53: KLO & CO. | klocowatches | C53: Alsta
A54: LAPS Watches | laps_paris | C54: Alterum
A55: Le Petit Poussoir | lepetitpoussoir | C55: ALTO Watches
A56: Le Pin Watches | lepinwatches | C56: Amida
A57: LORESUM | loresumwatches | C57: Ancon
A58: LOTH | lothwatches | C58: Andersen Genève
A59: maniloneofficial | manilone_official | C59: Andersmann
... A65: Metrical Watch | metricalwatch | C65: Anoma
C66: Anonimo
C67: anOrdaim
A68: Militadowatch | militadowatches | C68: Anpassa
A69: MONARKE Studio | monarkestudio__ | C69: Anstead
A70: MONOCHROME Watches | monochromewatches | C70: Antoine Martin
A71: MONOVANT WATCHES | monovantwatches | C71: Antoine Preziuso
A72: NAGA Time Co. | nagatimeco.watches | C72: Anton Suhanov
A73: NAMICA Watches | namica_watches | C73: Anura Rafael
A74: Nine Four Watches | ninefourwatches | C74: Aonic
A75: Niton | niton.swiss | C75: Aquadive
A76: Noctua | noctuawatchcorp | C76: Aquanautic
A77: NOHMAD | Relógios Masculinos | nohmadbrasil | C77: Aquastar
A78: NUNCIER | nuncier | C78: Aquatrident
A79: O&HoraPictor | o_horapictor | C79: Arach
A80: O.G | olivergallaugher | C80: Aramar Watch Co.
C81: Arcadia Watches
A82: Ontic Watches | onticwatches | C82: Arcaido
C83: Arcanaut
C84: Archetype
A85: PARADISI | paradisiwatches | C85: Archimede
A86: Parivas | parivas_watches | C86: ARC-TIC
A87: Pragma | pragma_watches | C87: Arctos
A88: Quantum Global | worldofquantum | C88: Arcturus
A89: Quill & Pad | quillandpad | C89: Ardío
A90: Rampart Studio | rampart.studio | C90: Arethusa
A91: Ratiowatches.com | ratiowatches | C91: Aristo
A92: REV★LUTION | revolution.watch | C92: Arken
A93: REWIND | rewindwatches_ | C93: Arlanch
A94: Roland Murphy | rgmwatches | C94: Armand Nicolet
A95: Rotoris | rotoris.world | C95: Armando Legin
A96: Schaefer & Companions | schaeferandcompanions | C96: Armida
... A105: Thorn watches | thornwatches | C105: Artel Rotec
C106: Arthur Oskar Stampfli
A107: TinCanTimepieces | tincantimepieces | C107: Artime
A108: Tool Watch Co. | toolwatchco | C108: Artisans De Genève
A109: TOPHILL Official | tophill.official | C109: Artur Akmaev
A110: TRITON WATCHES OFFICIAL | tritonwatch_official | C110: ArtyA
C111: Askania
C112: Aspen
C113: Asprey Watches
C114: Astor + Banks
C115: Astronic
C116: Ataelier Haute Complication
C117: Atelier de Chronomètrie Watches
A118: Wolbrook Watches | wolbrook | C118: Atelier Holgur
A119: Worden Watch Studio | worden.watch | C119: Atelier Jalaper
A120: Worn & Wound | wornandwound | C120: Atelier Loiseau
...

Sheet Relógios
A1: Marca | B1: Modelo | C1: Relógio | E1: Características
A2: Cuervo y Sobrinos | B2: Flechazo - 3142.1G | C2: https://cdn.sanity.io/images/qpozxwu2/cys-backend/e80d691c0ef40528645ef84391fec7a1d7476ae3-2953x5315.png
A3: Cuervo y Sobrinos | B3: Historiador Flameante - 3130.1FGR | C3: https://www.cuervoysobrinos.com/585-large_default/flameante.jpg
A4: Pequignet | B4: Royale 300 - 9050343 | C4: https://static.wixstatic.com/media/ee021f_fc006302d3d74af5a0ed2e25330dd741~mv2.png/v1/fill/w_800,h_1218,al_c/ee021f_fc006302d3d74af5a0ed2e25330dd741~mv2.png
A5: Pequignet | B5: Royale 300 - 9050473/36 | C5: https://static.wixstatic.com/media/ee021f_7cc9698edfdc4d729da31bd5f6bb00ff~mv2.png/v1/fill/w_800,h_1218,al_c/ee021f_7cc9698edfdc4d729da31bd5f6bb00ff~mv2.png
A6: Rado | B6: Centrix - R30130152 | C6: https://m.media-amazon.com/images/I/61ziyN9tGfL._AC_UF1000,1000_QL80_.jpg
A7: Rado | B7: Coupole - R22895165 | C7: http://cdn.shopify.com/s/files/1/0261/8900/4880/products/R22895165_1200x1200.jpg?v=1627044818
A8: Rado | B8: DiaMaster - 604.0070.3 | C8: https://www.uhrenschmuck24.ch/media/catalog/product/img/1/image/1080x1080/r/a/rado-diamaster-xxl-automatik-chronograph-7612819048369-1.jpg
A9: Rado | B9: DiaMaster - R14053106 | C9: https://www.rado.com/media/catalog/product/cache/af21745092e03eab5206bbb4f15452fb/r/g/rgb_cat_diamaster_773_6053_3_410_3.png
A10: Rado | B10: DiaMaster - R14070176 | C10: https://http2.mlstatic.com/D_NQ_NP_838357-MLB31670849222_082019-W.jpg
A11: Rado | B11: DiaMaster - R14129206 | C11: https://watchdreamer.com/sites/default/files/2021-09/R14129206_.png
A12: Rado | B12: HyperChrome - R32042305 | C12: https://www.hodinarstvibechyne.cz/res/crc-355981002/products/images/1920x1920/noenl/693678-r32042305-s.jpg
A13: Rado | B13: HyperChrome Captain Cook - R32145208 | C13: https://www.gregoryjewellers.com.au/wp-content/uploads/2022/08/RADO_r32145208_steel-43mm.jpg
... A68: Revue Thommen | B68: Aviator - 17000.6137 | C68: http://cdn.shopify.com/s/files/1/0614/9963/8003/products/revue-thommen-17000_6137-761175117502-chronolounge.png?v=1667874496
A69: Revue Thommen | B69: Aviator - 17000.6532 | C69: https://webassets.ashford.com/images/web/revue_thommen/17000.6532_FXA.jpg | D69: https://dbnext.watch-experts.net/api/images/watch/scale/400/5db05de18a4c9-cgk204-curare.jpg
A70: Revue Thommen | B70: Aviator - 17000.6535 | C70: https://cdn03.plentymarkets.com/ciw7a3ibeo67/item/images/8963507/full/Revue-Thommen-Herren-Armbanduhr-Automatic--Aviator-42-mm-Chronograph--Tachymeter-Armband-Leather-17000-6535-17000-6535_1.jpg
A71: Revue Thommen | B71: Aviator - 17000.6557 | C71: https://i.ebayimg.com/images/g/8EsAAOSwbdNfvDBr/s-l1600.jpg
A72: Revue Thommen | B72: Day Pointer - 10012.2512 | C72: https://cdn03.plentymarkets.com/ciw7a3ibeo67/item/images/8961773/full/Revue-Thommen-Herren-Armbanduhr-Automatik-DATE-POINTER-10012-2512-XLarge-10012-2512-Rev.jpg
A73: Revue Thommen | B73: Day Pointer - 10012.2537 | C73: https://www.kechiq.com/public/images/products/fdb43871-d38a-48b1-9629-ef8b414e4a44.jpg
A74: Revue Thommen | B74: Diver - 17030.6121 | C74: https://webassets.ashford.com/images/web/revue_thommen/17030.6121_FXA.jpg
A75: Revue Thommen | B75: Diver - 17030.6123 | C75: https://cdn2.jomashop.com/media/catalog/product/r/e/revue-thommen-diver-chronograph-automatic-blue-dial-mens-watch-170306123-170306123.jpg
A76: Revue Thommen | B76: Diver - 17030.6535 | C76: https://image.goxip.com/1pRGIr-zhaQIH9-UDZV0lRE9bFE=/fit-in/500x500/filters:format(jpg):quality(80):fill(white)/http:%2F%2Fres.cloudinary.com%2Fdjtnxo4ow%2Fimage%2Fprivate%2Fs--_F62uhCp--%2Fv1646357576%2Fimage1%2Fgawz48efkg2eyuzaattg.jpg%3Fdate=2022-03-03
A77: Revue Thommen | B77: Diver - 17571.2577 | C77: https://cdn.shopify.com/s/files/1/0552/3374/0989/products/17571.2537_250x250@2x.jpg?v=1649706958
A78: Revue Thommen | B78: Diver - 17571.2776 | C78: https://i.ebayimg.com/images/g/56AAAOSwL2JjvYwG/s-l1600.jpg
A79: Revue Thommen | B79: Specialities Moonphase - 16066.2532 | C79: https://www.gemnation.com/images/watches/Revu/16066.2532_ZM.jpg
A80: Revue Thommen | B80: Specialities Moonphase - 16066.2537 | C80: https://swissluxurywatches.ch/wp-content/uploads/2017/12/16066.2537_ZM.jpg
A81: Richard Mille | B81: RM21-01 - Tourbillon Aerodyne Limited Edition | C81: https://swisswatches-magazine.de/wp-content/uploads/sites/3/2021/04/Richard-Mille-RM-21-01-Tourbillon-Aerodyne-Titelbild.jpg
... A115: Tag Heuer | B115: Carrera Calibre 16 Lewis Hamilton Limited Edition - CV201MBA0794 | C115: https://cdn.trusted.com/images/20000102/17938_org.jpg
A116: Tag Heuer | B116: Carrera Calibre 16 Senna Edition - CBB2010.BA0906 | C116: https://cdn.shopify.com/s/files/1/0125/7792/products/TAG-397_TAG_Heuer_Watch_Carrera_Chronograph_Senna_Limited_CBB2010.BA0906.jpg?v=1435766803 | D116: https://cdn2.jomashop.com/media/catalog/product/t/a/tag-heuer-carrera-chronograph-automatic-mens-watch-cv2a1abba0738-cv2a1abba0738.jpg
A117: Tag Heuer | B117: Carrera Calibre 1887 - CAR2111.FC6291 | C117: https://www.tagheuer.com/on/demandware.static/-/Sites-tagheuer-master/default/dwba39e794/TAG_Heuer_Carrera/CAR2111_FC6291/CAR2111_FC6291_000913.png?impolicy=resizeTrim&width=884&height=1106
A118: Tag Heuer | B118: Carrera Calibre 1887 - CAR2C12.FC6327 | C118: https://www.tagheuer.com/on/demandware.static/-/Sites-tagheuer-master/default/dwa7e6c646/TAG_Heuer_Carrera/CAR2C12.FC6327/CAR2C12.FC6327_0913.png | D118: https://cdn.trusted.com/images/20000102/16910_org.jpg
A119: Tag Heuer | B119: Carrera Calibre 1887 - CAR2C90.FC6341 | C119: https://www.tagheuer.com/on/demandware.static/-/Sites-tagheuer-master/default/dw9a33d9cd/TAG_Heuer_Carrera/CAR2C90.FC6341/CAR2C90.FC6341_0913.png
A120: Tag Heuer | B120: Carrera Calibre 36 - CAR2B10.BA0799 | C120: https://s.turbifycdn.com/aah/movadobaby/tag-heuer-carrera-car2b10-ba0799-120.jpg
A121: Tag Heuer | B121: Carrera Calibre 36 - CAR2B11.BA0799 | C121: https://cdn.shopify.com/s/files/1/2500/4946/products/CAR2B11.BA0799_2048x.jpg?v=1532452875
A122: Tag Heuer | B122: Carrera Calibre 36 - CAR2B11.FC6235 | C122: https://s.turbifycdn.com/aah/movadobaby/tag-heuer-carrera-car2b11-fc6235-121.jpg
A123: Tag Heuer | B123: Carrera Calibre 360 - CV5011.FC6191 | C123: https://magazine.tagheuer.com/wp-content/uploads/2022/05/cv5011.fc6191-750x1027.jpg
A124: Tag Heuer | B124: Carrera Calibre 360 18K Rose Gold Limited Edition - CV5041.FC8164 | C124: https://cdn.trusted.com/images/20000102/16907_org.jpg
A125: Tag Heuer | B125: Carrera Calibre 360 PVD Tempus - CV5013.FC6232 | C125: https://magazine.tagheuer.com/wp-content/uploads/2022/05/cv5013.fc6232-693x1080.jpg
A126: Tag Heuer | B126: Carrera Calibre 360 Vanquish - CV5080 | C126: https://magazine.tagheuer.com/wp-content/uploads/2022/05/2227th-750x1002.jpg
A127: Tag Heuer | B127: Carrera Calibre 360 White Gold - CV5041.FC8164 | C127: https://magazine.tagheuer.com/wp-content/uploads/2022/05/cv5040.fc8160-789x1080.jpg | D127: https://www.kleenedelmetalen.nl/wp-content/uploads/2022/12/CAZ101G-Formula-1-Max-Verstappen-Limited-Edition-43-mm-1.jpeg
A128: Tag Heuer | B128: Carrera Calibre Heuer 01 - CAR201M.FT6156 | C128: https://www.tagheuer.com/on/demandware.static/-/Sites-tagheuer-master/default/dw65603724/TAG_Heuer_Carrera/CAR201M.FT6156/CAR201M.FT6156_0913.png?impolicy=resizeTrim&width=884&height=1106
A129: Tag Heuer | B129: Carrera Calibre Heuer 01 - CAR201W.FT6095 | C129: https://www.tagheuer.com/on/demandware.static/-/Sites-tagheuer-master/default/dw8e537b30/TAG_Heuer_Carrera/CAR201W.FT6095/CAR201W.FT6095_0913.png?impolicy=resizeTrim&width=884&height=1106
A130: Tag Heuer | B130: Carrera Calibre Heuer 01 - CAR208Z.BF0719 | C130: https://res.cloudinary.com/dp9dnliwc/image/upload/t_wm_ol/c_mfit,h_1200,w_1200/f_auto/q_auto/wmmedia/watch_images/large/car208zbf0719_1576694601.jpg
A131: Tag Heuer | B131: Carrera Calibre Heuer 01 - CAR2A1T.FT6052 | C131: https://www.tagheuer.com/on/demandware.static/-/Sites-tagheuer-master/default/dwe66ed2f7/TAG_Heuer_Carrera/CAR2A1T.FT6052/CAR2A1T.FT6052_0913.png?impolicy=resizeTrim&width=884&height=1106
A132: Tag Heuer | B132: Carrera Calibre Heuer 01 - CAR2A5C.FT6125 | C132: https://s.turbifycdn.com/aah/movadobaby/tag-heuer-carrera-car2a5c-ft6125-33.jpg
A133: Tag Heuer | B133: Carrera Calibre Heuer 01 - CAR2A8A.FT6072 | C133: https://www.tagheuer.com/on/demandware.static/-/Sites-tagheuer-master/default/dw73ecaf67/TAG_Heuer_Carrera/CAR2A8A.FT6072/CAR2A8A.FT6072_0913.png?impolicy=resizeTrim&width=884&height=1106
A134: Tag Heuer | B134: Carrera Calibre Heuer 02 - CBG2011.FC6430 | C134: https://www.prestigetime.com/images/watches/cbg2011.fc6430.jpg
A135: Tag Heuer | B135: Carrera Calibre Heuer 02 - CBG2A1Z.BA0658 | C135: https://da8t9y7300ntx.cloudfront.net/wp-content/uploads/sites/20/2021/12/CBG2A1Z.BA0658_1-1.png
A136: Tag Heuer | B136: Carrera Calibre Heuer 02 - CBG2A90.FT6173 | C136: https://www.prestigetime.com/images/watches/cbg2a90.ft6173.jpg | D136: https://www.demomi.com/2168/tag-heuer-grand-carrera-cav518bfc6237-cronografo-automatico-43-mm.jpg
A137: Tag Heuer | B137: Carrera Calibre Heuer 02 - CBN2012.FC6483 | C137: https://www.tagheuer.com/on/demandware.static/-/Sites-tagheuer-master/default/dwd4d88dcb/TAG_Heuer_Carrera/CBN2012.FC6483/CBN2012.FC6483_0913.png?impolicy=resize&width=1920 | D137: https://s.turbifycdn.com/aah/movadobaby/tag-heuer-carrera-car2b11-ba0799-130.jpg
A138: Tag Heuer | B138: Carrera Calibre Heuer 02 - CBN2014.BA0642 | C138: https://cdn.watchbase.com/watch/tag-heuer/carrera/cbn2014-ba0642-53.jpg
A139: Tag Heuer | B139: Carrera Calibre Heuer 02 - CBN2019.BA0642 | C139: https://cdn.shopify.com/s/files/1/0552/0988/5801/products/278568-image01-20220824144959_r2000x2000.jpg?v=1664442661
A140: Tag Heuer | B140: Carrera Calibre Heuer 02 - CBN2019.BA0642 | C140: https://cdn.shopify.com/s/files/1/0552/0988/5801/products/278568-image01-20220824144959_r2000x2000.jpg?v=1664442661
A141: Tag Heuer | B141: Carrera Calibre Heuer 02 - CBN2A1A.BA0643 | C141: https://juliookubo.vteximg.com.br/arquivos/ids/579715-1000-1000/CBN2A1AB_1_frontview.jpg?v=637949566541800000
A142: Tag Heuer | B142: Carrera Calibre Heuer 02 - CBN2A1A.FC6537 | C142: https://tagheuerforums.com/attachments/fc1c1830-3d50-4df7-b19b-884b74e66fa6-jpeg.1449141/
A143: Tag Heuer | B143: Carrera Calibre Heuer 02 - CBN2A1B.BA0643 | C143: https://juliookubo.vteximg.com.br/arquivos/ids/579781-1000-1000/CBN2A1BB_1_frontview.jpg?v=637949567874770000
A144: Tag Heuer | B144: Carrera Calibre Heuer 02 - CBN2A1E.BA0643 | C144: https://s.turbifycdn.com/aah/movadobaby/tag-heuer-carrera-limited-edition-men-s-watch-cbn2a1e-ba0643-13.jpg
A145: Tag Heuer | B145: Carrera Calibre Heuer 02 - CBN2A5A.FC6481 | C145: https://www.prestigetime.com/images/watches/cbn2a5a.fc6481.jpg
A146: Tag Heuer | B146: Carrera Calibre Heuer 02 - CBN2A5A.FC6481 | C146: https://cdn.shopify.com/s/files/1/2378/0799/products/CBN2A5A.FC6481_800x.jpg?v=1629190527
A147: Tag Heuer | B147: Carrera Calibre Heuer 02 "Year of the Rabbit Limited Edition" - CBN2A1L.FC6521 | C147: https://articleimg.xbiao.com/2023/0113/202301131673603805781.jpg
A148: Tag Heuer | B148: Carrera Calibre Heuer 02 160th Anniversary - CBK221B.FC6479 | C148: https://watchesofmayfair.com.au/media/catalog/product/cache/789a43c4e9a5a1e754ee1289235666c4/t/a/tag-heuer-carrera-limited-edition-39mm-cbk221b-fc6479_image-01.png
A149: Tag Heuer | B149: Carrera Calibre Heuer 02 160th Anniversary - CBN2A1D.BA0643 | C149: https://askme.watch/sites/default/files/watch/images/CBN2A1D.BA0643_SOLDAT.jpeg
A150: Tag Heuer | B150: Carrera Calibre Heuer 02 160th Anniversary - CBN2A1E.BA0643 | C150: https://s3.amazonaws.com/wpimages/wp-content/uploads/2022/12/10121158/CBN2A1E.png
A151: Tag Heuer | B151: Carrera Calibre Heuer 02 60th Anniversary - CBK221H.FC8317 | C151: https://magazine.tagheuer.com/wp-content/uploads/2023/01/cbk221h.fc8317_soldat-copie.png | D151: https://s.turbifycdn.com/aah/movadobaby/tag-heuer-monaco-caw211m-fc6324-63.jpg
A152: Tag Heuer | B152: Carrera Calibre Heuer 02 Bamford Limited Edition - | C152: https://www.bamfordwatchdepartment.com/wp-content/uploads/2021/03/carrera-21.png
A153: Tag Heuer | B153: Carrera Calibre Heuer 02 Bamford X TikTok Limited Edition - | C153: https://www.bamfordwatchdepartment.com/wp-content/uploads/2021/12/tiktokcarrera-main.png
A154: Tag Heuer | B154: Carrera Calibre Heuer 02 Jack Heuer's 88th birthday - CBN2041.FC8306 | C154: https://www.tagheuer.com/on/demandware.static/-/Sites-tagheuer-master/default/dwe4e22289/TAG_Heuer_Carrera/CBN2041.FC8306/CBN2041.FC8306_0913.png?impolicy=resize&width=1920
A155: Tag Heuer | B155: Carrera Calibre Heuer 02 Senna Special Edition - CBG2013.BA0657 | C155: https://www.tagheuer.com/on/demandware.static/-/Sites-tagheuer-master/default/dwd8f2832b/TAG_Heuer_Carrera/CBG2013.BA0657/CBG2013.BA0657_0913.png
A156: Tag Heuer | B156: Carrera Calibre Heuer 02 Skeleton Japan Limited Edition - CBG2019.BA0662 | C156: https://cdn.swisswatchexpo.com/productphotos/1/4/tag-heuer-carrera-japan-limited-skeletonized-dial-watch-cbg2019-box-card-39162_959f0_md.jpg
A157: Tag Heuer | B157: Carrera Calibre Heuer-02T Nordic Tourbillon - CAR5A98.FC6471 | C157: https://cdn.shopify.com/s/files/1/0150/4172/4464/products/hvelplund_s01_073.png?v=1664872875
A158: Tag Heuer | B158: Carrera Calibre Heuer-02T Tourbillon - CAR5A8W.FT6071 | C158: https://da8t9y7300ntx.cloudfront.net/wp-content/uploads/sites/20/2021/12/CAR5A8W.FT6071_1.png
A159: Tag Heuer | B159: Carrera Calibre Heuer-02T Tourbillon COSC - CAR5A8C.BF0707 | C159: https://www.bankslyon.co.uk/wp-content/uploads/2021/11/1616596754-8751-1200x1899.jpg
A160: Tag Heuer | B160: Carrera Calibre Heuer-02T Tourbillon COSC - CAR5A8Y.FT6072 | C160: https://www.tagheuer.com/on/demandware.static/-/Sites-tagheuer-master/default/dw9025b359/TAG_Heuer_Carrera/CAR5A8Y.FT6072/CAR5A8Y.FT6072_0913.png?impolicy=resizeTrim&width=884&height=1106
A161: Tag Heuer | B161: Carrera Calibre Heuer-02T Tourbillon Nanograph - CAR5A8K.FT6172 | C161: https://www.prestigetime.com/images/watches/car5a8k.ft6172.jpg
A162: Tag Heuer | B162: Carrera Calibre Heuer-02T Tourbillon Polychrome Chronograph - CAR5A8AF.FC6415 | C162: https://content.thewosgroup.com/productimage/17382086/17382086_1.jpg?impolicy=zoom
A163: Tag Heuer | B163: Carrera Calibre16 - CV2A1AB.BA0738 | C163: https://hanak-brno.cz/wp-content/uploads/2022/12/cv2a1ab-ba0738-135945_1.jpg
... A177: Tag Heuer | B177: Formula 1 - CAZ101V.BA0842 | C177: https://d3vwg1uuu70k7b.cloudfront.net/Custom/Content/Products/56/74/56740_relogio-tag-heuer-formula-1-edicao-especial-indy-500-aco-quartzo-43mm_m1_637572082190887862.jpg
A178: Tag Heuer | B178: Formula 1 Calibre 16 - CAU2012.FT6038 | C178: https://s.turbifycdn.com/aah/movadobaby/tag-heuer-formula-one-cau2012-ft6038-35.jpg | D178: https://cdn2.jomashop.com/media/catalog/product/t/a/tag-heuer-chronograph-automatic-black-dial-mens-watch-cbn2a5afc6481-cbn2a5afc6481.jpg
A179: Tag Heuer | B179: Formula 1 Calibre 16 - CAZ2012.BA0876 | C179: https://juliookubo.vteximg.com.br/arquivos/ids/701986-1000-1000/CAZ2012B_1_frontview.jpg?v=638120847654700000
A180: Tag Heuer | B180: Formula 1 Cristiano Ronaldo - CAZ1113.FC8189 | C180: https://www.giulian.bg/media/catalog/product/cache/2/image/9df78eab33525d08d6e5fb8d27136e95/1/7/17956_1.jpg
A181: Tag Heuer | B181: Formula 1 Mario Kart Special Edition - CAZ201E.FC6517 | C181: https://rayandscott.com/images/tag-heuer-mario-kart-special-edition-formula-1-caz201e-fc6517-p40769-25745_image.jpg
A182: Tag Heuer | B182: Formula 1 Max Verstappen Limited Edition - CAZ101G.FT8030 | C182: https://yourwatchhub.static-vds.nl/2017/08/tag-heuer-formula-1-no-33-max-verstappen-2017-CAZ101G-FT8030.jpg
A183: Tag Heuer | B183: Formula 1 Senna Edition - CAZ101AF.BA0637 | C183: https://www.rologia.com.gr/images/product/CAZ101AF.BA0637.png
A184: Tag Heuer | B184: Formula 1 Senna Edition - CAZ2017.BA0647 | C184: https://lojavivara.vtexassets.com/arquivos/ids/233133/Relogio-TAG-Heuer-Formula-1-Masculino-Aco-CAZ2017BA0647-m4730072_set.jpg?v=1764620041
A185: Tag Heuer | B185: Formula 1 X Mario Kart Tourbillon - CAZ5080.FC6517 | C185: https://media.gq-magazine.co.uk/photos/6347db66bd70b3f668459974/master/w_1600%2Cc_limit/Gaming-watches-TAG-1.jpg
A186: Tag Heuer | B186: Grand Carrera Calibre 17 - CAV511A.BA0902 | C186: https://cdn.shopify.com/s/files/1/0102/3737/8657/products/57_0ec05ea2-464c-4e6a-8b4d-ceec2db478ce.jpg?v=1583356932
A187: Tag Heuer | B187: Grand Carrera Calibre 17 - CAV511B.FC6225 | C187: https://crystalgroup.ua/wp-content/uploads/2021/09/85769c045b2c04805490e7c2d68633a1-1.jpg
A188: Tag Heuer | B188: Grand Carrera Calibre 17 - CAV514B.FC8171 | C188: https://s.turbifycdn.com/aah/movadobaby/tag-heuer-grand-carrera-cav514b-fc8171-28.jpg
A189: Tag Heuer | B189: Grand Carrera Calibre 17 - CAV518B.FC6237 | C189: https://cdn2.jomashop.com/media/catalog/product/t/a/tag-heuer-grand-carrera-chronometer-men_s-watch-cav518b.fc6237_5.jpg
A190: Tag Heuer | B190: Grand Carrera Calibre 17 - CAV518E.FT6016 | C190: https://askme.watch/sites/default/files/styles/watch_full_content/public/watch/images/5497ed4de3196_tag-heuer-grand-carrera-chronographe-automatique-calibre-17-rs2-43mm-cav518eft6016.png?itok=8KochFeW
... A218: Tag Heuer | B218: Monaco V4 Platinum Limited Edition - WAW2080.FC6288 | C218: https://s.yimg.com/aah/movadobaby/tag-heuer-monaco-waw2080-fc6288-182.jpg
A219: Tag Heuer | B219: Monaco - CS2111.FC8119 | C219: https://www.horobox.com/Cms_Data/Contents/SampleBusiness/Media/Haberler/TAG-Heuer-Monaco-Heuer-02/cs2111-fc8119-tag-heuer-monaco.jpg | D219: https://watchbox-cdn.imgix.net/posted-product-images/636941622365588425-Tag%20Heuer-CS2111-8000.jpg?w=1400&h=1400&auto=compress,format
A220: Tag Heuer | B220: Carrera Calbre 1887 Monaco Grand Prix Limited Edition - CAR2A83.FT6033 | C220: https://cdn.swisswatchexpo.com/productphotos/1/21/tag-heuer-carrera-monaco-grand-prix-special-edition-mens-watch-car2a83-31521_347a1_md.jpg
A221: Tag Heuer | B221: Carrera Calibre 16 - CV2A1S.FC6236 | C221: https://www.tagheuer.com/on/demandware.static/-/Sites-tagheuer-master/default/dwfc92e166/TAG_Heuer_Carrera/CV2A1S.FC6236/CV2A1S.FC6236_0913.png
A222: Tag Heuer | B222: Carrera Calibre 16 - CV2A1R.BA0799 | C222: https://content.thewosgroup.com/productimage/17381097/17381097_1.jpg?impolicy=zoom
A223: Tag Heuer | B223: Carrera Calibre Heuer 02 - CBN2011.BA0642 | C223: https://juliookubo.vteximg.com.br/arquivos/ids/722085-1000-1000/CBN2011B_1_frontview.jpg?v=638167289548400000
A224: Tag Heuer | B224: Monaco Calibre 11 Steve McQueen Limited Series - CAW211D.FC6300 | C224: https://s.turbifycdn.com/aah/movadobaby/tag-heuer-monaco-caw211d-fc6300-28.jpg
A225: Tag Heuer | B225: Monaco Calibre 11 - CAW211P.FC6183 | C225: https://s.turbifycdn.com/aah/movadobaby/tag-heuer-monaco-caw211p-fc6183-70.jpg
A226: Temption | B226: CGK-204 2232 | C226: https://www.watchuseek.com/cdn-cgi/image/format=auto,onerror=redirect,width=1920,height=1920,fit=scale-down/https://www.watchuseek.com/attachments/6abd7886-dc0b-422c-88f3-f4ad6f37d362-jpeg.16871302/
A227: Temption | B227: CGK-204 Coral | C227: http://swisstime.co/images/products/p374_i1130_temption-chronograph-cgk-204-moonphase-chrono.jpg
...

Sheet Tabela de faixa de preços
A1: 1 | B1: 1 | C1: 1000
A2: 2 | B2: 1001 | C2: 5000 | G2: https://monochrome-watches.com/all-brands/
A3: 3 | B3: 5001 | C3: 10000
A4: 4 | B4: 10001 | C4: 20000
A5: 5 | B5: 20001 | C5: 40000
A6: 6 | B6: 40001 | C6: 70000
A7: 7 | B7: 70001 | C7: 100000
A8: 8 | B8: 100001 | C8: 350000
A9: 9 | B9: 350001 | C9: 600000
A10: 10 | B10: 600000 | C10: 200000000
